{
"meta":{"test_sets":[],"test_metrics":[],"learn_metrics":[{"best_value":"Min","name":"RMSE"}],"launch_mode":"Train","parameters":"","iteration_count":1000,"learn_sets":["learn"],"name":"experiment"},
"iterations":[
{"learn":[14.61268541],"iteration":0,"passed_time":0.1427641774,"remaining_time":142.6214133},
{"learn":[14.23196558],"iteration":1,"passed_time":0.1439251194,"remaining_time":71.81863457},
{"learn":[13.86674177],"iteration":2,"passed_time":0.1448455266,"remaining_time":48.13699667},
{"learn":[13.49946468],"iteration":3,"passed_time":0.1458480152,"remaining_time":36.31615579},
{"learn":[13.16661202],"iteration":4,"passed_time":0.1469095833,"remaining_time":29.23500708},
{"learn":[12.85632158],"iteration":5,"passed_time":0.1478220301,"remaining_time":24.48918299},
{"learn":[12.56784336],"iteration":6,"passed_time":0.1487798775,"remaining_time":21.10548834},
{"learn":[12.31617801],"iteration":7,"passed_time":0.149833827,"remaining_time":18.57939455},
{"learn":[12.01509946],"iteration":8,"passed_time":0.1509507704,"remaining_time":16.62135705},
{"learn":[11.71512571],"iteration":9,"passed_time":0.1518865471,"remaining_time":15.03676816},
{"learn":[11.43264457],"iteration":10,"passed_time":0.152885871,"remaining_time":13.74582968},
{"learn":[11.17973129],"iteration":11,"passed_time":0.1538682298,"remaining_time":12.66848425},
{"learn":[10.93746433],"iteration":12,"passed_time":0.1548966688,"remaining_time":11.7602317},
{"learn":[10.69387075],"iteration":13,"passed_time":0.1557928394,"remaining_time":10.97226712},
{"learn":[10.4615922],"iteration":14,"passed_time":0.156740325,"remaining_time":10.29261467},
{"learn":[10.2299235],"iteration":15,"passed_time":0.1576763468,"remaining_time":9.697095331},
{"learn":[10.01419731],"iteration":16,"passed_time":0.1586238563,"remaining_time":9.172191221},
{"learn":[9.795856918],"iteration":17,"passed_time":0.159744283,"remaining_time":8.714938104},
{"learn":[9.60040151],"iteration":18,"passed_time":0.1608036573,"remaining_time":8.302546726},
{"learn":[9.418664989],"iteration":19,"passed_time":0.1617875389,"remaining_time":7.927589408},
{"learn":[9.249278645],"iteration":20,"passed_time":0.1627354381,"remaining_time":7.586571136},
{"learn":[9.090113396],"iteration":21,"passed_time":0.163652469,"remaining_time":7.275096122},
{"learn":[8.909548708],"iteration":22,"passed_time":0.1646595874,"remaining_time":6.99445291},
{"learn":[8.740140208],"iteration":23,"passed_time":0.1655045837,"remaining_time":6.730519737},
{"learn":[8.59377682],"iteration":24,"passed_time":0.1663806794,"remaining_time":6.488846495},
{"learn":[8.453885414],"iteration":25,"passed_time":0.1674552394,"remaining_time":6.273130892},
{"learn":[8.317732234],"iteration":26,"passed_time":0.1684308706,"remaining_time":6.069749522},
{"learn":[8.180896085],"iteration":27,"passed_time":0.1692865716,"remaining_time":5.876662414},
{"learn":[8.053220863],"iteration":28,"passed_time":0.1700402607,"remaining_time":5.693417006},
{"learn":[7.924234474],"iteration":29,"passed_time":0.1708828727,"remaining_time":5.525212883},
{"learn":[7.818879511],"iteration":30,"passed_time":0.1716581333,"remaining_time":5.365701005},
{"learn":[7.719346395],"iteration":31,"passed_time":0.1730164684,"remaining_time":5.23374817},
{"learn":[7.624163594],"iteration":32,"passed_time":0.173868953,"remaining_time":5.094887199},
{"learn":[7.524952543],"iteration":33,"passed_time":0.1748041378,"remaining_time":4.966494032},
{"learn":[7.424464745],"iteration":34,"passed_time":0.1756939926,"remaining_time":4.844134367},
{"learn":[7.327482321],"iteration":35,"passed_time":0.1765234252,"remaining_time":4.726905054},
{"learn":[7.238666841],"iteration":36,"passed_time":0.1773740643,"remaining_time":4.616519566},
{"learn":[7.158842395],"iteration":37,"passed_time":0.178445788,"remaining_time":4.517496001},
{"learn":[7.074348246],"iteration":38,"passed_time":0.179147607,"remaining_time":4.414380777},
{"learn":[6.992269093],"iteration":39,"passed_time":0.1798076161,"remaining_time":4.315382786},
{"learn":[6.925219745],"iteration":40,"passed_time":0.1808129483,"remaining_time":4.229258961},
{"learn":[6.86013671],"iteration":41,"passed_time":0.1816035088,"remaining_time":4.142289558},
{"learn":[6.786739622],"iteration":42,"passed_time":0.1823209378,"remaining_time":4.057700871},
{"learn":[6.73057926],"iteration":43,"passed_time":0.1831677503,"remaining_time":3.979735665},
{"learn":[6.666356486],"iteration":44,"passed_time":0.1838609009,"remaining_time":3.901936897},
{"learn":[6.606182832],"iteration":45,"passed_time":0.1847353894,"remaining_time":3.831251338},
{"learn":[6.547854615],"iteration":46,"passed_time":0.1855273173,"remaining_time":3.761862413},
{"learn":[6.49240675],"iteration":47,"passed_time":0.186251162,"remaining_time":3.69398138},
{"learn":[6.431317261],"iteration":48,"passed_time":0.1869625607,"remaining_time":3.628599902},
{"learn":[6.377586395],"iteration":49,"passed_time":0.1878978935,"remaining_time":3.570059976},
{"learn":[6.327558015],"iteration":50,"passed_time":0.1888906508,"remaining_time":3.5148476},
{"learn":[6.282040317],"iteration":51,"passed_time":0.1897501167,"remaining_time":3.459290588},
{"learn":[6.237655841],"iteration":52,"passed_time":0.1908110046,"remaining_time":3.40939663},
{"learn":[6.192792003],"iteration":53,"passed_time":0.1916739003,"remaining_time":3.357842772},
{"learn":[6.150579347],"iteration":54,"passed_time":0.1924209989,"remaining_time":3.306142617},
{"learn":[6.115693845],"iteration":55,"passed_time":0.1931333873,"remaining_time":3.255677101},
{"learn":[6.078780782],"iteration":56,"passed_time":0.1938500349,"remaining_time":3.20702777},
{"learn":[6.045146957],"iteration":57,"passed_time":0.194527785,"remaining_time":3.159399542},
{"learn":[6.008080327],"iteration":58,"passed_time":0.1952736093,"remaining_time":3.114448583},
{"learn":[5.977575734],"iteration":59,"passed_time":0.1959470493,"remaining_time":3.069837106},
{"learn":[5.948036502],"iteration":60,"passed_time":0.1966185943,"remaining_time":3.026637049},
{"learn":[5.914888282],"iteration":61,"passed_time":0.1972853135,"remaining_time":2.984735872},
{"learn":[5.884957796],"iteration":62,"passed_time":0.1979833037,"remaining_time":2.944608819},
{"learn":[5.849539885],"iteration":63,"passed_time":0.1986134181,"remaining_time":2.90472124},
{"learn":[5.821387627],"iteration":64,"passed_time":0.1992713569,"remaining_time":2.866441826},
{"learn":[5.797012279],"iteration":65,"passed_time":0.1999217318,"remaining_time":2.829195416},
{"learn":[5.768685095],"iteration":66,"passed_time":0.2005865584,"remaining_time":2.793242671},
{"learn":[5.755484587],"iteration":67,"passed_time":0.2009386012,"remaining_time":2.754040828},
{"learn":[5.731887055],"iteration":68,"passed_time":0.2015826153,"remaining_time":2.719904563},
{"learn":[5.707148487],"iteration":69,"passed_time":0.2022345876,"remaining_time":2.68683095},
{"learn":[5.685365039],"iteration":70,"passed_time":0.2029409272,"remaining_time":2.655381991},
{"learn":[5.663541834],"iteration":71,"passed_time":0.2035986345,"remaining_time":2.624160178},
{"learn":[5.638108797],"iteration":72,"passed_time":0.2046393936,"remaining_time":2.598639971},
{"learn":[5.619204893],"iteration":73,"passed_time":0.2054438386,"remaining_time":2.57082425},
{"learn":[5.598472793],"iteration":74,"passed_time":0.2064270836,"remaining_time":2.545934032},
{"learn":[5.577007075],"iteration":75,"passed_time":0.2072409834,"remaining_time":2.519614061},
{"learn":[5.562637084],"iteration":76,"passed_time":0.2079697208,"remaining_time":2.492935744},
{"learn":[5.54729991],"iteration":77,"passed_time":0.2086618545,"remaining_time":2.466490126},
{"learn":[5.530737623],"iteration":78,"passed_time":0.2093913724,"remaining_time":2.441132328},
{"learn":[5.513704873],"iteration":79,"passed_time":0.2100789869,"remaining_time":2.415908349},
{"learn":[5.501575529],"iteration":80,"passed_time":0.210808696,"remaining_time":2.391767797},
{"learn":[5.484080734],"iteration":81,"passed_time":0.2114545095,"remaining_time":2.367259021},
{"learn":[5.472178894],"iteration":82,"passed_time":0.2121410154,"remaining_time":2.343774833},
{"learn":[5.458923342],"iteration":83,"passed_time":0.2127586737,"remaining_time":2.32008268},
{"learn":[5.451382371],"iteration":84,"passed_time":0.213235512,"remaining_time":2.29541757},
{"learn":[5.441410748],"iteration":85,"passed_time":0.21391439,"remaining_time":2.273462238},
{"learn":[5.434047468],"iteration":86,"passed_time":0.2143491432,"remaining_time":2.249434112},
{"learn":[5.422107497],"iteration":87,"passed_time":0.2150271595,"remaining_time":2.22846329},
{"learn":[5.40731265],"iteration":88,"passed_time":0.2156931119,"remaining_time":2.207824999},
{"learn":[5.396360181],"iteration":89,"passed_time":0.2163802279,"remaining_time":2.187844527},
{"learn":[5.383793239],"iteration":90,"passed_time":0.217044145,"remaining_time":2.16805635},
{"learn":[5.369605034],"iteration":91,"passed_time":0.2178224568,"remaining_time":2.149812943},
{"learn":[5.357467333],"iteration":92,"passed_time":0.2185720064,"remaining_time":2.131664622},
{"learn":[5.341109968],"iteration":93,"passed_time":0.219693115,"remaining_time":2.117467683},
{"learn":[5.330529276],"iteration":94,"passed_time":0.2206807012,"remaining_time":2.102274048},
{"learn":[5.319862075],"iteration":95,"passed_time":0.22141675,"remaining_time":2.085007729},
{"learn":[5.313052243],"iteration":96,"passed_time":0.2220890175,"remaining_time":2.067488482},
{"learn":[5.299677207],"iteration":97,"passed_time":0.2227326726,"remaining_time":2.050049701},
{"learn":[5.287546698],"iteration":98,"passed_time":0.2234005048,"remaining_time":2.03317025},
{"learn":[5.279803754],"iteration":99,"passed_time":0.2240664868,"remaining_time":2.016598381},
{"learn":[5.272254612],"iteration":100,"passed_time":0.2247333405,"remaining_time":2.000349239},
{"learn":[5.268813888],"iteration":101,"passed_time":0.2250530032,"remaining_time":1.981348989},
{"learn":[5.258113767],"iteration":102,"passed_time":0.2257091897,"remaining_time":1.965642167},
{"learn":[5.251018576],"iteration":103,"passed_time":0.2263767753,"remaining_time":1.950322987},
{"learn":[5.24171237],"iteration":104,"passed_time":0.2270538742,"remaining_time":1.935363975},
{"learn":[5.233984943],"iteration":105,"passed_time":0.227703616,"remaining_time":1.920443705},
{"learn":[5.226240449],"iteration":106,"passed_time":0.2283694664,"remaining_time":1.905924612},
{"learn":[5.220541644],"iteration":107,"passed_time":0.2290648629,"remaining_time":1.89190609},
{"learn":[5.211712096],"iteration":108,"passed_time":0.2297920314,"remaining_time":1.878391743},
{"learn":[5.203388597],"iteration":109,"passed_time":0.2304726018,"remaining_time":1.864732869},
{"learn":[5.196026544],"iteration":110,"passed_time":0.2311740211,"remaining_time":1.851474818},
{"learn":[5.188716772],"iteration":111,"passed_time":0.231903124,"remaining_time":1.838660483},
{"learn":[5.182163132],"iteration":112,"passed_time":0.2326003524,"remaining_time":1.825809846},
{"learn":[5.17764747],"iteration":113,"passed_time":0.2332699302,"remaining_time":1.812957527},
{"learn":[5.170548056],"iteration":114,"passed_time":0.2342125465,"remaining_time":1.802418293},
{"learn":[5.165901827],"iteration":115,"passed_time":0.2349076918,"remaining_time":1.790158617},
{"learn":[5.160333668],"iteration":116,"passed_time":0.235740095,"remaining_time":1.779132512},
{"learn":[5.148953243],"iteration":117,"passed_time":0.2364822965,"remaining_time":1.767604962},
{"learn":[5.144729126],"iteration":118,"passed_time":0.2370249071,"remaining_time":1.754781035},
{"learn":[5.139939946],"iteration":119,"passed_time":0.237685621,"remaining_time":1.743027887},
{"learn":[5.132898872],"iteration":120,"passed_time":0.2383331959,"remaining_time":1.731362638},
{"learn":[5.129073077],"iteration":121,"passed_time":0.2389612988,"remaining_time":1.719737872},
{"learn":[5.127123916],"iteration":122,"passed_time":0.2393050425,"remaining_time":1.706264409},
{"learn":[5.121282057],"iteration":123,"passed_time":0.2399612315,"remaining_time":1.69520999},
{"learn":[5.114489821],"iteration":124,"passed_time":0.2406101024,"remaining_time":1.684270717},
{"learn":[5.107777291],"iteration":125,"passed_time":0.241260727,"remaining_time":1.673506948},
{"learn":[5.103518754],"iteration":126,"passed_time":0.2419376978,"remaining_time":1.663083545},
{"learn":[5.101133351],"iteration":127,"passed_time":0.2423534134,"remaining_time":1.651032629},
{"learn":[5.096462705],"iteration":128,"passed_time":0.2430230236,"remaining_time":1.640876384},
{"learn":[5.08562082],"iteration":129,"passed_time":0.2436985967,"remaining_time":1.630905993},
{"learn":[5.080483682],"iteration":130,"passed_time":0.244373737,"remaining_time":1.621074637},
{"learn":[5.07437499],"iteration":131,"passed_time":0.2450350032,"remaining_time":1.611290779},
{"learn":[5.070683732],"iteration":132,"passed_time":0.2457586302,"remaining_time":1.60205062},
{"learn":[5.06432037],"iteration":133,"passed_time":0.2464436392,"remaining_time":1.592687997},
{"learn":[5.057436484],"iteration":134,"passed_time":0.2471104448,"remaining_time":1.583337294},
{"learn":[5.053254656],"iteration":135,"passed_time":0.2478008964,"remaining_time":1.574264518},
{"learn":[5.04801663],"iteration":136,"passed_time":0.2485904828,"remaining_time":1.565938589},
{"learn":[5.045680836],"iteration":137,"passed_time":0.2494926952,"remaining_time":1.558425386},
{"learn":[5.041857933],"iteration":138,"passed_time":0.2503165235,"remaining_time":1.550521775},
{"learn":[5.035264888],"iteration":139,"passed_time":0.2510983251,"remaining_time":1.54246114},
{"learn":[5.028771948],"iteration":140,"passed_time":0.2517660966,"remaining_time":1.533809056},
{"learn":[5.024912247],"iteration":141,"passed_time":0.2523817463,"remaining_time":1.524954495},
{"learn":[5.02239068],"iteration":142,"passed_time":0.2530079667,"remaining_time":1.516278514},
{"learn":[5.017110572],"iteration":143,"passed_time":0.2537122224,"remaining_time":1.508178211},
{"learn":[5.010707886],"iteration":144,"passed_time":0.2543459568,"remaining_time":1.49976409},
{"learn":[5.004389868],"iteration":145,"passed_time":0.2549992454,"remaining_time":1.491570929},
{"learn":[4.997628683],"iteration":146,"passed_time":0.2555906265,"remaining_time":1.483121118},
{"learn":[4.991497851],"iteration":147,"passed_time":0.256192687,"remaining_time":1.474838982},
{"learn":[4.988345253],"iteration":148,"passed_time":0.2568621248,"remaining_time":1.467044753},
{"learn":[4.98460423],"iteration":149,"passed_time":0.2575297982,"remaining_time":1.459335523},
{"learn":[4.982441783],"iteration":150,"passed_time":0.258152137,"remaining_time":1.451464664},
{"learn":[4.977461771],"iteration":151,"passed_time":0.258812615,"remaining_time":1.443901957},
{"learn":[4.973601586],"iteration":152,"passed_time":0.2595656572,"remaining_time":1.436941906},
{"learn":[4.968328804],"iteration":153,"passed_time":0.260207788,"remaining_time":1.429453173},
{"learn":[4.9640736],"iteration":154,"passed_time":0.2608908237,"remaining_time":1.422275781},
{"learn":[4.960865882],"iteration":155,"passed_time":0.2615420807,"remaining_time":1.415009718},
{"learn":[4.957014156],"iteration":156,"passed_time":0.2622140099,"remaining_time":1.407938919},
{"learn":[4.952244852],"iteration":157,"passed_time":0.262904054,"remaining_time":1.401045655},
{"learn":[4.949695675],"iteration":158,"passed_time":0.2637098006,"remaining_time":1.394842405},
{"learn":[4.946584698],"iteration":159,"passed_time":0.2646513872,"remaining_time":1.389419783},
{"learn":[4.940192834],"iteration":160,"passed_time":0.2655329644,"remaining_time":1.383740106},
{"learn":[4.936727994],"iteration":161,"passed_time":0.2663159074,"remaining_time":1.377609447},
{"learn":[4.932342063],"iteration":162,"passed_time":0.2669739594,"remaining_time":1.370903092},
{"learn":[4.925830838],"iteration":163,"passed_time":0.2676242843,"remaining_time":1.364231108},
{"learn":[4.922571773],"iteration":164,"passed_time":0.2682641414,"remaining_time":1.35757914},
{"learn":[4.918395814],"iteration":165,"passed_time":0.269274883,"remaining_time":1.352862966},
{"learn":[4.911142452],"iteration":166,"passed_time":0.2709613583,"remaining_time":1.351561745},
{"learn":[4.908276131],"iteration":167,"passed_time":0.27472827,"remaining_time":1.360559051},
{"learn":[4.904584645],"iteration":168,"passed_time":0.2768990915,"remaining_time":1.361557071},
{"learn":[4.89795517],"iteration":169,"passed_time":0.2799775455,"remaining_time":1.366949193},
{"learn":[4.895556491],"iteration":170,"passed_time":0.281117028,"remaining_time":1.3628422},
{"learn":[4.890591233],"iteration":171,"passed_time":0.2823890123,"remaining_time":1.359407571},
{"learn":[4.884629277],"iteration":172,"passed_time":0.2835114871,"remaining_time":1.355283236},
{"learn":[4.880550786],"iteration":173,"passed_time":0.2844895486,"remaining_time":1.350507857},
{"learn":[4.876384842],"iteration":174,"passed_time":0.285571166,"remaining_time":1.346264068},
{"learn":[4.872638238],"iteration":175,"passed_time":0.2863730875,"remaining_time":1.340746728},
{"learn":[4.869137118],"iteration":176,"passed_time":0.287028394,"remaining_time":1.334600951},
{"learn":[4.863587157],"iteration":177,"passed_time":0.2877324128,"remaining_time":1.328741816},
{"learn":[4.858028614],"iteration":178,"passed_time":0.2890194719,"remaining_time":1.325614449},
{"learn":[4.853838176],"iteration":179,"passed_time":0.2900421111,"remaining_time":1.321302951},
{"learn":[4.853462329],"iteration":180,"passed_time":0.29041413,"remaining_time":1.314083826},
{"learn":[4.851573196],"iteration":181,"passed_time":0.2911408068,"remaining_time":1.308533956},
{"learn":[4.848442087],"iteration":182,"passed_time":0.2918170389,"remaining_time":1.302811589},
{"learn":[4.845547104],"iteration":183,"passed_time":0.2926351813,"remaining_time":1.297773413},
{"learn":[4.839868817],"iteration":184,"passed_time":0.2937136921,"remaining_time":1.293927887},
{"learn":[4.836336958],"iteration":185,"passed_time":0.2953623183,"remaining_time":1.292607135},
{"learn":[4.831124789],"iteration":186,"passed_time":0.296613351,"remaining_time":1.289554301},
{"learn":[4.827407333],"iteration":187,"passed_time":0.2975244972,"remaining_time":1.285052615},
{"learn":[4.824088918],"iteration":188,"passed_time":0.2984984891,"remaining_time":1.280858596},
{"learn":[4.820934539],"iteration":189,"passed_time":0.2994532203,"remaining_time":1.27661636},
{"learn":[4.816975227],"iteration":190,"passed_time":0.3002664895,"remaining_time":1.271809372},
{"learn":[4.812340486],"iteration":191,"passed_time":0.3010273419,"remaining_time":1.266823397},
{"learn":[4.806402747],"iteration":192,"passed_time":0.3019856111,"remaining_time":1.262706674},
{"learn":[4.801521788],"iteration":193,"passed_time":0.302851772,"remaining_time":1.258239836},
{"learn":[4.797601172],"iteration":194,"passed_time":0.3035791985,"remaining_time":1.253237204},
{"learn":[4.792694629],"iteration":195,"passed_time":0.3044462116,"remaining_time":1.248850786},
{"learn":[4.789794613],"iteration":196,"passed_time":0.305329114,"remaining_time":1.244564866},
{"learn":[4.785367055],"iteration":197,"passed_time":0.3061683733,"remaining_time":1.240136542},
{"learn":[4.780376856],"iteration":198,"passed_time":0.3069668221,"remaining_time":1.235580023},
{"learn":[4.776691261],"iteration":199,"passed_time":0.3076594414,"remaining_time":1.230637766},
{"learn":[4.773470753],"iteration":200,"passed_time":0.3084632816,"remaining_time":1.22617991},
{"learn":[4.77207327],"iteration":201,"passed_time":0.3097083492,"remaining_time":1.2235013},
{"learn":[4.767347177],"iteration":202,"passed_time":0.3105102496,"remaining_time":1.219096891},
{"learn":[4.763983068],"iteration":203,"passed_time":0.3113530524,"remaining_time":1.214887401},
{"learn":[4.761588849],"iteration":204,"passed_time":0.312072121,"remaining_time":1.210230908},
{"learn":[4.758558086],"iteration":205,"passed_time":0.3126974179,"remaining_time":1.205251213},
{"learn":[4.753678804],"iteration":206,"passed_time":0.3133464932,"remaining_time":1.200404682},
{"learn":[4.746510889],"iteration":207,"passed_time":0.3140397548,"remaining_time":1.195766759},
{"learn":[4.744840601],"iteration":208,"passed_time":0.3147149383,"remaining_time":1.191098164},
{"learn":[4.741702222],"iteration":209,"passed_time":0.3153878602,"remaining_time":1.186459093},
{"learn":[4.739352853],"iteration":210,"passed_time":0.3160540984,"remaining_time":1.181832624},
{"learn":[4.735539287],"iteration":211,"passed_time":0.3167115527,"remaining_time":1.177210866},
{"learn":[4.730726751],"iteration":212,"passed_time":0.3173523628,"remaining_time":1.172564834},
{"learn":[4.726416092],"iteration":213,"passed_time":0.3180290971,"remaining_time":1.168088179},
{"learn":[4.721293082],"iteration":214,"passed_time":0.3186668357,"remaining_time":1.163504493},
{"learn":[4.718443695],"iteration":215,"passed_time":0.3192773611,"remaining_time":1.15885857},
{"learn":[4.711627962],"iteration":216,"passed_time":0.3199246205,"remaining_time":1.154382387},
{"learn":[4.709790764],"iteration":217,"passed_time":0.3205619331,"remaining_time":1.14990565},
{"learn":[4.706913073],"iteration":218,"passed_time":0.3211779215,"remaining_time":1.14538793},
{"learn":[4.703846389],"iteration":219,"passed_time":0.3218737223,"remaining_time":1.141188652},
{"learn":[4.701001135],"iteration":220,"passed_time":0.3225192986,"remaining_time":1.136844043},
{"learn":[4.700380864],"iteration":221,"passed_time":0.3232432075,"remaining_time":1.132807277},
{"learn":[4.695837486],"iteration":222,"passed_time":0.3241496129,"remaining_time":1.129436095},
{"learn":[4.691242996],"iteration":223,"passed_time":0.324993001,"remaining_time":1.12586861},
{"learn":[4.690284609],"iteration":224,"passed_time":0.3257471989,"remaining_time":1.12201813},
{"learn":[4.68827119],"iteration":225,"passed_time":0.3264177943,"remaining_time":1.117908729},
{"learn":[4.686922425],"iteration":226,"passed_time":0.3270600532,"remaining_time":1.113733133},
{"learn":[4.686085874],"iteration":227,"passed_time":0.3276978179,"remaining_time":1.109573313},
{"learn":[4.683230741],"iteration":228,"passed_time":0.3283235419,"remaining_time":1.105403715},
{"learn":[4.6773487],"iteration":229,"passed_time":0.3290062026,"remaining_time":1.101455548},
{"learn":[4.671462906],"iteration":230,"passed_time":0.3296335045,"remaining_time":1.097351363},
{"learn":[4.664799601],"iteration":231,"passed_time":0.3302971407,"remaining_time":1.093397431},
{"learn":[4.660979386],"iteration":232,"passed_time":0.3309569279,"remaining_time":1.089459072},
{"learn":[4.656281279],"iteration":233,"passed_time":0.3316151793,"remaining_time":1.085543707},
{"learn":[4.651997094],"iteration":234,"passed_time":0.3322705237,"remaining_time":1.081646598},
{"learn":[4.650151977],"iteration":235,"passed_time":0.3329016165,"remaining_time":1.077698453},
{"learn":[4.648478046],"iteration":236,"passed_time":0.3335403332,"remaining_time":1.073802845},
{"learn":[4.646364602],"iteration":237,"passed_time":0.3342045311,"remaining_time":1.070016188},
{"learn":[4.642635873],"iteration":238,"passed_time":0.3348541519,"remaining_time":1.066209245},
{"learn":[4.640860821],"iteration":239,"passed_time":0.3354885036,"remaining_time":1.062380261},
{"learn":[4.639446822],"iteration":240,"passed_time":0.3361264592,"remaining_time":1.058589139},
{"learn":[4.637120072],"iteration":241,"passed_time":0.3367857336,"remaining_time":1.054890852},
{"learn":[4.633769267],"iteration":242,"passed_time":0.3375745136,"remaining_time":1.051621016},
{"learn":[4.630491517],"iteration":243,"passed_time":0.3385392484,"remaining_time":1.048916688},
{"learn":[4.627813333],"iteration":244,"passed_time":0.3392718924,"remaining_time":1.045511342},
{"learn":[4.622496304],"iteration":245,"passed_time":0.3401134485,"remaining_time":1.042461545},
{"learn":[4.618979301],"iteration":246,"passed_time":0.3408686467,"remaining_time":1.03916636},
{"learn":[4.616563458],"iteration":247,"passed_time":0.3415045865,"remaining_time":1.035530037},
{"learn":[4.614759385],"iteration":248,"passed_time":0.3421052151,"remaining_time":1.031811311},
{"learn":[4.61251363],"iteration":249,"passed_time":0.3427570786,"remaining_time":1.028271236},
{"learn":[4.608796693],"iteration":250,"passed_time":0.3434737811,"remaining_time":1.024947658},
{"learn":[4.60847774],"iteration":251,"passed_time":0.3441200232,"remaining_time":1.021435624},
{"learn":[4.605195659],"iteration":252,"passed_time":0.344772453,"remaining_time":1.017964515},
{"learn":[4.60103766],"iteration":253,"passed_time":0.3454250584,"remaining_time":1.014516116},
{"learn":[4.599325598],"iteration":254,"passed_time":0.3460514493,"remaining_time":1.011013058},
{"learn":[4.597012808],"iteration":255,"passed_time":0.346672672,"remaining_time":1.007517453},
{"learn":[4.594161533],"iteration":256,"passed_time":0.3473075974,"remaining_time":1.004083832},
{"learn":[4.592197259],"iteration":257,"passed_time":0.3479386916,"remaining_time":1.000660888},
{"learn":[4.58952828],"iteration":258,"passed_time":0.3485720549,"remaining_time":0.9972659948},
{"learn":[4.585816572],"iteration":259,"passed_time":0.3492112861,"remaining_time":0.993909045},
{"learn":[4.582934052],"iteration":260,"passed_time":0.3498649409,"remaining_time":0.9906137598},
{"learn":[4.582234842],"iteration":261,"passed_time":0.350460029,"remaining_time":0.9871736694},
{"learn":[4.57571562],"iteration":262,"passed_time":0.3511182212,"remaining_time":0.9839320494},
{"learn":[4.571197349],"iteration":263,"passed_time":0.3519113687,"remaining_time":0.98108624},
{"learn":[4.56723703],"iteration":264,"passed_time":0.3526553782,"remaining_time":0.978119634},
{"learn":[4.560335567],"iteration":265,"passed_time":0.3536103485,"remaining_time":0.975751864},
{"learn":[4.554709345],"iteration":266,"passed_time":0.3544807853,"remaining_time":0.9731626054},
{"learn":[4.552806306],"iteration":267,"passed_time":0.3552940731,"remaining_time":0.9704300802},
{"learn":[4.550766241],"iteration":268,"passed_time":0.3559466899,"remaining_time":0.9672752056},
{"learn":[4.549216045],"iteration":269,"passed_time":0.3565625662,"remaining_time":0.9640395309},
{"learn":[4.547687452],"iteration":270,"passed_time":0.3572677768,"remaining_time":0.961063503},
{"learn":[4.545642435],"iteration":271,"passed_time":0.3578829649,"remaining_time":0.9578632295},
{"learn":[4.543930359],"iteration":272,"passed_time":0.3585265579,"remaining_time":0.954757537},
{"learn":[4.541029943],"iteration":273,"passed_time":0.3591569206,"remaining_time":0.9516347605},
{"learn":[4.537781449],"iteration":274,"passed_time":0.3597509379,"remaining_time":0.9484342909},
{"learn":[4.53066128],"iteration":275,"passed_time":0.360431149,"remaining_time":0.9454788112},
{"learn":[4.526763956],"iteration":276,"passed_time":0.361203489,"remaining_time":0.9427802259},
{"learn":[4.522036004],"iteration":277,"passed_time":0.3618695877,"remaining_time":0.9398195768},
{"learn":[4.515307629],"iteration":278,"passed_time":0.3625480186,"remaining_time":0.9369072453},
{"learn":[4.51109143],"iteration":279,"passed_time":0.3632178383,"remaining_time":0.9339887271},
{"learn":[4.508233494],"iteration":280,"passed_time":0.3638875648,"remaining_time":0.9310859755},
{"learn":[4.502555629],"iteration":281,"passed_time":0.3645129602,"remaining_time":0.9280861894},
{"learn":[4.500081355],"iteration":282,"passed_time":0.3651608926,"remaining_time":0.9251602826},
{"learn":[4.495281743],"iteration":283,"passed_time":0.365935745,"remaining_time":0.9225703994},
{"learn":[4.492138869],"iteration":284,"passed_time":0.3667816708,"remaining_time":0.92017156},
{"learn":[4.491708261],"iteration":285,"passed_time":0.3676170727,"remaining_time":0.9177573075},
{"learn":[4.489398865],"iteration":286,"passed_time":0.3693590275,"remaining_time":0.9176062251},
{"learn":[4.485796373],"iteration":287,"passed_time":0.3701570121,"remaining_time":0.9151103911},
{"learn":[4.479542205],"iteration":288,"passed_time":0.3710974011,"remaining_time":0.9129766513},
{"learn":[4.475986993],"iteration":289,"passed_time":0.3721359837,"remaining_time":0.9110915462},
{"learn":[4.468661855],"iteration":290,"passed_time":0.372920096,"remaining_time":0.9085922614},
{"learn":[4.463785664],"iteration":291,"passed_time":0.3736089087,"remaining_time":0.9058736554},
{"learn":[4.460445831],"iteration":292,"passed_time":0.3756250186,"remaining_time":0.9063716319},
{"learn":[4.45692492],"iteration":293,"passed_time":0.3769925248,"remaining_time":0.9052949746},
{"learn":[4.454031688],"iteration":294,"passed_time":0.3784397296,"remaining_time":0.9044068115},
{"learn":[4.451672391],"iteration":295,"passed_time":0.3797279902,"remaining_time":0.9031368415},
{"learn":[4.45031553],"iteration":296,"passed_time":0.3808850834,"remaining_time":0.9015562748},
{"learn":[4.446782666],"iteration":297,"passed_time":0.3851757921,"remaining_time":0.9073604231},
{"learn":[4.444369689],"iteration":298,"passed_time":0.3863478138,"remaining_time":0.9057853428},
{"learn":[4.44411683],"iteration":299,"passed_time":0.3877066418,"remaining_time":0.9046488308},
{"learn":[4.440876943],"iteration":300,"passed_time":0.3888397735,"remaining_time":0.9029867166},
{"learn":[4.439336453],"iteration":301,"passed_time":0.3898549266,"remaining_time":0.9010554263},
{"learn":[4.436666901],"iteration":302,"passed_time":0.391075896,"remaining_time":0.8996036288},
{"learn":[4.433043336],"iteration":303,"passed_time":0.3923265176,"remaining_time":0.8982212377},
{"learn":[4.431419305],"iteration":304,"passed_time":0.3946783013,"remaining_time":0.899348916},
{"learn":[4.428859646],"iteration":305,"passed_time":0.3963317567,"remaining_time":0.8988700626},
{"learn":[4.424552441],"iteration":306,"passed_time":0.3973919139,"remaining_time":0.8970442878},
{"learn":[4.422706391],"iteration":307,"passed_time":0.3981848388,"remaining_time":0.8946230793},
{"learn":[4.421427994],"iteration":308,"passed_time":0.3989014963,"remaining_time":0.8920418574},
{"learn":[4.418733158],"iteration":309,"passed_time":0.3997178392,"remaining_time":0.8896945453},
{"learn":[4.415656941],"iteration":310,"passed_time":0.4007008763,"remaining_time":0.8877263786},
{"learn":[4.410747417],"iteration":311,"passed_time":0.4015560702,"remaining_time":0.8854826163},
{"learn":[4.408126521],"iteration":312,"passed_time":0.4024408167,"remaining_time":0.8833125913},
{"learn":[4.407843853],"iteration":313,"passed_time":0.4035988595,"remaining_time":0.8817478267},
{"learn":[4.405219398],"iteration":314,"passed_time":0.4045742037,"remaining_time":0.8797883478},
{"learn":[4.402708465],"iteration":315,"passed_time":0.4054586983,"remaining_time":0.8776384483},
{"learn":[4.40104971],"iteration":316,"passed_time":0.4062437695,"remaining_time":0.8752823172},
{"learn":[4.400830038],"iteration":317,"passed_time":0.4070529577,"remaining_time":0.8729877898},
{"learn":[4.39784288],"iteration":318,"passed_time":0.4077240373,"remaining_time":0.8704077411},
{"learn":[4.393741845],"iteration":319,"passed_time":0.4084609735,"remaining_time":0.8679795687},
{"learn":[4.393425936],"iteration":320,"passed_time":0.4091937121,"remaining_time":0.8655530545},
{"learn":[4.390505974],"iteration":321,"passed_time":0.4099863957,"remaining_time":0.8632632804},
{"learn":[4.390305136],"iteration":322,"passed_time":0.4112897499,"remaining_time":0.862053129},
{"learn":[4.38568203],"iteration":323,"passed_time":0.412198703,"remaining_time":0.8600195162},
{"learn":[4.383057135],"iteration":324,"passed_time":0.4130962082,"remaining_time":0.8579690478},
{"learn":[4.380662684],"iteration":325,"passed_time":0.4138792768,"remaining_time":0.855689057},
{"learn":[4.37805727],"iteration":326,"passed_time":0.4146429856,"remaining_time":0.8533783771},
{"learn":[4.373708319],"iteration":327,"passed_time":0.4154275429,"remaining_time":0.851119844},
{"learn":[4.36887921],"iteration":328,"passed_time":0.4161235977,"remaining_time":0.8486897693},
{"learn":[4.367895929],"iteration":329,"passed_time":0.4168520911,"remaining_time":0.8463360638},
{"learn":[4.362140573],"iteration":330,"passed_time":0.4175333931,"remaining_time":0.8438967975},
{"learn":[4.361931924],"iteration":331,"passed_time":0.4181491599,"remaining_time":0.8413362614},
{"learn":[4.359656377],"iteration":332,"passed_time":0.4187953677,"remaining_time":0.8388483792},
{"learn":[4.354281355],"iteration":333,"passed_time":0.4194727874,"remaining_time":0.8364337617},
{"learn":[4.348589447],"iteration":334,"passed_time":0.4201347701,"remaining_time":0.8339988721},
{"learn":[4.346355698],"iteration":335,"passed_time":0.4208083971,"remaining_time":0.8315975467},
{"learn":[4.343894047],"iteration":336,"passed_time":0.4214884994,"remaining_time":0.8292192139},
{"learn":[4.341561356],"iteration":337,"passed_time":0.4221668532,"remaining_time":0.8268475054},
{"learn":[4.338869061],"iteration":338,"passed_time":0.4228598929,"remaining_time":0.8245144224},
{"learn":[4.333720063],"iteration":339,"passed_time":0.4235622318,"remaining_time":0.8222090381},
{"learn":[4.330892223],"iteration":340,"passed_time":0.4243522003,"remaining_time":0.8200824047},
{"learn":[4.328311474],"iteration":341,"passed_time":0.4253990294,"remaining_time":0.8184577817},
{"learn":[4.324580133],"iteration":342,"passed_time":0.4262244824,"remaining_time":0.8164124925},
{"learn":[4.323354432],"iteration":343,"passed_time":0.4271248371,"remaining_time":0.8145171313},
{"learn":[4.323159553],"iteration":344,"passed_time":0.4278857976,"remaining_time":0.8123628912},
{"learn":[4.318639682],"iteration":345,"passed_time":0.4285780159,"remaining_time":0.8100867699},
{"learn":[4.312712208],"iteration":346,"passed_time":0.4292753371,"remaining_time":0.8078293808},
{"learn":[4.311461062],"iteration":347,"passed_time":0.4299267682,"remaining_time":0.8054949794},
{"learn":[4.311178356],"iteration":348,"passed_time":0.4305934827,"remaining_time":0.8031987314},
{"learn":[4.311102505],"iteration":349,"passed_time":0.431236891,"remaining_time":0.8008685118},
{"learn":[4.310232308],"iteration":350,"passed_time":0.4318616604,"remaining_time":0.7985134405},
{"learn":[4.305128197],"iteration":351,"passed_time":0.4325469552,"remaining_time":0.7962796221},
{"learn":[4.304595496],"iteration":352,"passed_time":0.4331914789,"remaining_time":0.7939798494},
{"learn":[4.3004992],"iteration":353,"passed_time":0.4338673863,"remaining_time":0.7917466994},
{"learn":[4.297581524],"iteration":354,"passed_time":0.4345197901,"remaining_time":0.7894796186},
{"learn":[4.297355825],"iteration":355,"passed_time":0.4351151019,"remaining_time":0.7871183305},
{"learn":[4.295758715],"iteration":356,"passed_time":0.4357400902,"remaining_time":0.7848203865},
{"learn":[4.292500657],"iteration":357,"passed_time":0.4363526727,"remaining_time":0.7825095415},
{"learn":[4.290797586],"iteration":358,"passed_time":0.4370042119,"remaining_time":0.7802777153},
{"learn":[4.286410608],"iteration":359,"passed_time":0.4376528483,"remaining_time":0.778049508},
{"learn":[4.280278245],"iteration":360,"passed_time":0.4382973773,"remaining_time":0.7758227814},
{"learn":[4.279941283],"iteration":361,"passed_time":0.4389393964,"remaining_time":0.7736003726},
{"learn":[4.274426275],"iteration":362,"passed_time":0.439986856,"remaining_time":0.7720981467},
{"learn":[4.273567658],"iteration":363,"passed_time":0.4407586572,"remaining_time":0.7701167746},
{"learn":[4.269488271],"iteration":364,"passed_time":0.4414502381,"remaining_time":0.7680024691},
{"learn":[4.266838205],"iteration":365,"passed_time":0.4421034605,"remaining_time":0.7658294916},
{"learn":[4.263456509],"iteration":366,"passed_time":0.4427753526,"remaining_time":0.7636969978},
{"learn":[4.260360204],"iteration":367,"passed_time":0.4435115402,"remaining_time":0.7616828625},
{"learn":[4.255120549],"iteration":368,"passed_time":0.4442163768,"remaining_time":0.7596220427},
{"learn":[4.252582211],"iteration":369,"passed_time":0.4449966701,"remaining_time":0.7576970328},
{"learn":[4.247857931],"iteration":370,"passed_time":0.4457076719,"remaining_time":0.755660716},
{"learn":[4.245288911],"iteration":371,"passed_time":0.446728501,"remaining_time":0.7541545662},
{"learn":[4.24048515],"iteration":372,"passed_time":0.4480672686,"remaining_time":0.7531854622},
{"learn":[4.2378365],"iteration":373,"passed_time":0.449278485,"remaining_time":0.7520008866},
{"learn":[4.236751063],"iteration":374,"passed_time":0.450239648,"remaining_time":0.7503994133},
{"learn":[4.233240093],"iteration":375,"passed_time":0.4510493871,"remaining_time":0.7485500467},
{"learn":[4.230358421],"iteration":376,"passed_time":0.4518542966,"remaining_time":0.7466982143},
{"learn":[4.225853583],"iteration":377,"passed_time":0.4525891076,"remaining_time":0.7447365739},
{"learn":[4.224702126],"iteration":378,"passed_time":0.4532544159,"remaining_time":0.7426675259},
{"learn":[4.224361982],"iteration":379,"passed_time":0.4540820463,"remaining_time":0.7408707071},
{"learn":[4.223787954],"iteration":380,"passed_time":0.4549860535,"remaining_time":0.7392030632},
{"learn":[4.22144054],"iteration":381,"passed_time":0.4557413644,"remaining_time":0.7372988565},
{"learn":[4.217739335],"iteration":382,"passed_time":0.4565505586,"remaining_time":0.7354874535},
{"learn":[4.215611665],"iteration":383,"passed_time":0.4572260019,"remaining_time":0.7334667113},
{"learn":[4.210236863],"iteration":384,"passed_time":0.4578840263,"remaining_time":0.731425133},
{"learn":[4.208454294],"iteration":385,"passed_time":0.4585727067,"remaining_time":0.7294394868},
{"learn":[4.207446501],"iteration":386,"passed_time":0.4592147643,"remaining_time":0.7273866939},
{"learn":[4.204985442],"iteration":387,"passed_time":0.4598579188,"remaining_time":0.7253429029},
{"learn":[4.202796622],"iteration":388,"passed_time":0.4604858198,"remaining_time":0.7232823545},
{"learn":[4.199774004],"iteration":389,"passed_time":0.4611233458,"remaining_time":0.7212442075},
{"learn":[4.199458358],"iteration":390,"passed_time":0.4617383964,"remaining_time":0.7191782185},
{"learn":[4.19751254],"iteration":391,"passed_time":0.4623452412,"remaining_time":0.7171069047},
{"learn":[4.195201346],"iteration":392,"passed_time":0.462997104,"remaining_time":0.7151125754},
{"learn":[4.190593508],"iteration":393,"passed_time":0.4636533754,"remaining_time":0.7131318414},
{"learn":[4.187212054],"iteration":394,"passed_time":0.4642775444,"remaining_time":0.7111086439},
{"learn":[4.184984466],"iteration":395,"passed_time":0.4648940213,"remaining_time":0.7090807799},
{"learn":[4.182832144],"iteration":396,"passed_time":0.465542253,"remaining_time":0.7071082584},
{"learn":[4.179752812],"iteration":397,"passed_time":0.4661622318,"remaining_time":0.7050996572},
{"learn":[4.17878934],"iteration":398,"passed_time":0.4667966516,"remaining_time":0.7031197685},
{"learn":[4.174548229],"iteration":399,"passed_time":0.4674278133,"remaining_time":0.7011417199},
{"learn":[4.168872556],"iteration":400,"passed_time":0.4681512844,"remaining_time":0.6993082776},
{"learn":[4.163926494],"iteration":401,"passed_time":0.468845767,"remaining_time":0.6974372355},
{"learn":[4.159485076],"iteration":402,"passed_time":0.4695138982,"remaining_time":0.6955329956},
{"learn":[4.155926102],"iteration":403,"passed_time":0.4702295859,"remaining_time":0.6937050326},
{"learn":[4.153540115],"iteration":404,"passed_time":0.4709315212,"remaining_time":0.6918623583},
{"learn":[4.150983044],"iteration":405,"passed_time":0.4716474294,"remaining_time":0.6900457464},
{"learn":[4.146539132],"iteration":406,"passed_time":0.4723976859,"remaining_time":0.688284589},
{"learn":[4.144869174],"iteration":407,"passed_time":0.4730397442,"remaining_time":0.6863713936},
{"learn":[4.142825962],"iteration":408,"passed_time":0.473694721,"remaining_time":0.684483081},
{"learn":[4.142467378],"iteration":409,"passed_time":0.4743446641,"remaining_time":0.6825935411},
{"learn":[4.141800768],"iteration":410,"passed_time":0.4749722543,"remaining_time":0.6806779995},
{"learn":[4.140107084],"iteration":411,"passed_time":0.4755938959,"remaining_time":0.6787602204},
{"learn":[4.136243196],"iteration":412,"passed_time":0.4762509362,"remaining_time":0.6768990305},
{"learn":[4.133618439],"iteration":413,"passed_time":0.4768963534,"remaining_time":0.6750272055},
{"learn":[4.131053025],"iteration":414,"passed_time":0.4775461713,"remaining_time":0.6731674944},
{"learn":[4.128379975],"iteration":415,"passed_time":0.4782096498,"remaining_time":0.6713327776},
{"learn":[4.127068571],"iteration":416,"passed_time":0.47884405,"remaining_time":0.6694630243},
{"learn":[4.125969877],"iteration":417,"passed_time":0.4794798314,"remaining_time":0.667601105},
{"learn":[4.123893633],"iteration":418,"passed_time":0.4801050973,"remaining_time":0.6657304571},
{"learn":[4.119643722],"iteration":419,"passed_time":0.4807842229,"remaining_time":0.6639401174},
{"learn":[4.11465686],"iteration":420,"passed_time":0.4814186006,"remaining_time":0.6620935149},
{"learn":[4.111565986],"iteration":421,"passed_time":0.48201902,"remaining_time":0.6602061459},
{"learn":[4.106322452],"iteration":422,"passed_time":0.482700262,"remaining_time":0.6584351092},
{"learn":[4.104222175],"iteration":423,"passed_time":0.4833883525,"remaining_time":0.6566785166},
{"learn":[4.103008002],"iteration":424,"passed_time":0.4840483238,"remaining_time":0.6548889087},
{"learn":[4.099176337],"iteration":425,"passed_time":0.4846773245,"remaining_time":0.6530628739},
{"learn":[4.096525716],"iteration":426,"passed_time":0.4852950792,"remaining_time":0.6512273546},
{"learn":[4.094967724],"iteration":427,"passed_time":0.4859729439,"remaining_time":0.6494778595},
{"learn":[4.094683584],"iteration":428,"passed_time":0.4865606628,"remaining_time":0.6476133764},
{"learn":[4.091096563],"iteration":429,"passed_time":0.4871988132,"remaining_time":0.6458216827},
{"learn":[4.089178677],"iteration":430,"passed_time":0.4878397694,"remaining_time":0.6440390459},
{"learn":[4.085335077],"iteration":431,"passed_time":0.488453407,"remaining_time":0.6422257759},
{"learn":[4.084852122],"iteration":432,"passed_time":0.4890609882,"remaining_time":0.6404101162},
{"learn":[4.080322952],"iteration":433,"passed_time":0.4897200942,"remaining_time":0.6386672197},
{"learn":[4.077449519],"iteration":434,"passed_time":0.4903696638,"remaining_time":0.6369169196},
{"learn":[4.076568374],"iteration":435,"passed_time":0.4910414859,"remaining_time":0.6352004543},
{"learn":[4.076071793],"iteration":436,"passed_time":0.4916638968,"remaining_time":0.6334251119},
{"learn":[4.075027644],"iteration":437,"passed_time":0.4922951359,"remaining_time":0.6316663616},
{"learn":[4.07020837],"iteration":438,"passed_time":0.492925211,"remaining_time":0.6299112605},
{"learn":[4.06833694],"iteration":439,"passed_time":0.4935510378,"remaining_time":0.6281558662},
{"learn":[4.063936568],"iteration":440,"passed_time":0.4941970412,"remaining_time":0.6264311701},
{"learn":[4.061734926],"iteration":441,"passed_time":0.4948684369,"remaining_time":0.6247434113},
{"learn":[4.060815619],"iteration":442,"passed_time":0.4954921524,"remaining_time":0.6230002909},
{"learn":[4.056407489],"iteration":443,"passed_time":0.4961350232,"remaining_time":0.6212862002},
{"learn":[4.05238936],"iteration":444,"passed_time":0.4969550813,"remaining_time":0.6197979104},
{"learn":[4.049685254],"iteration":445,"passed_time":0.4976683308,"remaining_time":0.6181799446},
{"learn":[4.045162016],"iteration":446,"passed_time":0.4983814376,"remaining_time":0.6165658501},
{"learn":[4.042955482],"iteration":447,"passed_time":0.499042043,"remaining_time":0.6148910887},
{"learn":[4.041467663],"iteration":448,"passed_time":0.4996694244,"remaining_time":0.6131800732},
{"learn":[4.038920476],"iteration":449,"passed_time":0.500293932,"remaining_time":0.6114703614},
{"learn":[4.036694383],"iteration":450,"passed_time":0.5009716775,"remaining_time":0.6098302681},
{"learn":[4.034999007],"iteration":451,"passed_time":0.5015713568,"remaining_time":0.6080997866},
{"learn":[4.031928018],"iteration":452,"passed_time":0.5021741409,"remaining_time":0.6063780466},
{"learn":[4.028718143],"iteration":453,"passed_time":0.5028262482,"remaining_time":0.604720554},
{"learn":[4.027401978],"iteration":454,"passed_time":0.5034686009,"remaining_time":0.6030557967},
{"learn":[4.025930598],"iteration":455,"passed_time":0.5041031988,"remaining_time":0.6013862722},
{"learn":[4.021074523],"iteration":456,"passed_time":0.5047647794,"remaining_time":0.5997533374},
{"learn":[4.020268486],"iteration":457,"passed_time":0.5053691599,"remaining_time":0.5980569534},
{"learn":[4.017986361],"iteration":458,"passed_time":0.5059965196,"remaining_time":0.596392412},
{"learn":[4.014814804],"iteration":459,"passed_time":0.5066367439,"remaining_time":0.5947474819},
{"learn":[4.009704796],"iteration":460,"passed_time":0.5072769717,"remaining_time":0.5931069149},
{"learn":[4.008440457],"iteration":461,"passed_time":0.5079233994,"remaining_time":0.591477898},
{"learn":[4.004854849],"iteration":462,"passed_time":0.5085754981,"remaining_time":0.5898597029},
{"learn":[4.000898028],"iteration":463,"passed_time":0.5092438637,"remaining_time":0.5882644632},
{"learn":[3.996617985],"iteration":464,"passed_time":0.5098988194,"remaining_time":0.5866577815},
{"learn":[3.995443319],"iteration":465,"passed_time":0.5106233357,"remaining_time":0.5851348954},
{"learn":[3.990771995],"iteration":466,"passed_time":0.5113176956,"remaining_time":0.5835810102},
{"learn":[3.989249359],"iteration":467,"passed_time":0.5119635366,"remaining_time":0.5819756442},
{"learn":[3.986599538],"iteration":468,"passed_time":0.5125882041,"remaining_time":0.5803503974},
{"learn":[3.985628919],"iteration":469,"passed_time":0.5132823842,"remaining_time":0.5788077949},
{"learn":[3.985086112],"iteration":470,"passed_time":0.5139492304,"remaining_time":0.5772380953},
{"learn":[3.98466839],"iteration":471,"passed_time":0.5146076067,"remaining_time":0.5756627465},
{"learn":[3.984233894],"iteration":472,"passed_time":0.5152729325,"remaining_time":0.5740990178},
{"learn":[3.981855845],"iteration":473,"passed_time":0.5159265491,"remaining_time":0.5725260862},
{"learn":[3.978684264],"iteration":474,"passed_time":0.5166102867,"remaining_time":0.5709903169},
{"learn":[3.974361269],"iteration":475,"passed_time":0.5173167751,"remaining_time":0.5694831726},
{"learn":[3.972074049],"iteration":476,"passed_time":0.5179876092,"remaining_time":0.5679402927},
{"learn":[3.97191982],"iteration":477,"passed_time":0.5186901194,"remaining_time":0.5664356534},
{"learn":[3.969616848],"iteration":478,"passed_time":0.5193707551,"remaining_time":0.5649105708},
{"learn":[3.968533527],"iteration":479,"passed_time":0.5200041309,"remaining_time":0.5633378084},
{"learn":[3.967568753],"iteration":480,"passed_time":0.5206585857,"remaining_time":0.5617916964},
{"learn":[3.966232553],"iteration":481,"passed_time":0.5212874187,"remaining_time":0.5602217487},
{"learn":[3.961522393],"iteration":482,"passed_time":0.5219825714,"remaining_time":0.5587266862},
{"learn":[3.955829553],"iteration":483,"passed_time":0.5227169382,"remaining_time":0.5572767357},
{"learn":[3.954248095],"iteration":484,"passed_time":0.5233570083,"remaining_time":0.5557296068},
{"learn":[3.951922606],"iteration":485,"passed_time":0.5240399398,"remaining_time":0.5542315413},
{"learn":[3.94978202],"iteration":486,"passed_time":0.5246881759,"remaining_time":0.5527002756},
{"learn":[3.949518999],"iteration":487,"passed_time":0.5253475552,"remaining_time":0.5511843202},
{"learn":[3.945431216],"iteration":488,"passed_time":0.5261331334,"remaining_time":0.5498037447},
{"learn":[3.943249086],"iteration":489,"passed_time":0.5268897018,"remaining_time":0.5483954039},
{"learn":[3.941981548],"iteration":490,"passed_time":0.5275591571,"remaining_time":0.5468994114},
{"learn":[3.936600517],"iteration":491,"passed_time":0.5287924656,"remaining_time":0.5459889685},
{"learn":[3.934476885],"iteration":492,"passed_time":0.5294853957,"remaining_time":0.5445214921},
{"learn":[3.93045798],"iteration":493,"passed_time":0.5302505107,"remaining_time":0.5431310899},
{"learn":[3.925977375],"iteration":494,"passed_time":0.5313470134,"remaining_time":0.5420812965},
{"learn":[3.92457993],"iteration":495,"passed_time":0.5329630875,"remaining_time":0.5415592664},
{"learn":[3.919849146],"iteration":496,"passed_time":0.534272233,"remaining_time":0.5407221996},
{"learn":[3.919681964],"iteration":497,"passed_time":0.5359426965,"remaining_time":0.5402474571},
{"learn":[3.917633027],"iteration":498,"passed_time":0.5371161583,"remaining_time":0.5392689285},
{"learn":[3.916616419],"iteration":499,"passed_time":0.5382828309,"remaining_time":0.5382828309},
{"learn":[3.912896166],"iteration":500,"passed_time":0.5394362602,"remaining_time":0.5372828221},
{"learn":[3.912769674],"iteration":501,"passed_time":0.5404998508,"remaining_time":0.5361930791},
{"learn":[3.909373788],"iteration":502,"passed_time":0.5415831516,"remaining_time":0.5351229152},
{"learn":[3.906706036],"iteration":503,"passed_time":0.5426838181,"remaining_time":0.5340697892},
{"learn":[3.903895664],"iteration":504,"passed_time":0.543944177,"remaining_time":0.5331730052},
{"learn":[3.902982967],"iteration":505,"passed_time":0.544942412,"remaining_time":0.5320188765},
{"learn":[3.900905528],"iteration":506,"passed_time":0.545653604,"remaining_time":0.5305862461},
{"learn":[3.897463465],"iteration":507,"passed_time":0.5463412217,"remaining_time":0.5291336242},
{"learn":[3.895918033],"iteration":508,"passed_time":0.5476304392,"remaining_time":0.5282643333},
{"learn":[3.893921936],"iteration":509,"passed_time":0.548742524,"remaining_time":0.5272232094},
{"learn":[3.890237934],"iteration":510,"passed_time":0.5498644633,"remaining_time":0.5261912378},
{"learn":[3.887311613],"iteration":511,"passed_time":0.5509828742,"remaining_time":0.525155552},
{"learn":[3.884869735],"iteration":512,"passed_time":0.5521285808,"remaining_time":0.5241454559},
{"learn":[3.882101231],"iteration":513,"passed_time":0.5534510084,"remaining_time":0.5233019262},
{"learn":[3.88060368],"iteration":514,"passed_time":0.5545475135,"remaining_time":0.5222437748},
{"learn":[3.877726076],"iteration":515,"passed_time":0.5556397107,"remaining_time":0.521181434},
{"learn":[3.874938145],"iteration":516,"passed_time":0.5567386918,"remaining_time":0.5201253156},
{"learn":[3.874340833],"iteration":517,"passed_time":0.5578631199,"remaining_time":0.51909271},
{"learn":[3.873105224],"iteration":518,"passed_time":0.5601824036,"remaining_time":0.5191671216},
{"learn":[3.869800236],"iteration":519,"passed_time":0.5615794963,"remaining_time":0.5183810735},
{"learn":[3.867932518],"iteration":520,"passed_time":0.5629011164,"remaining_time":0.5175232912},
{"learn":[3.866666962],"iteration":521,"passed_time":0.5649015991,"remaining_time":0.5172853723},
{"learn":[3.865527652],"iteration":522,"passed_time":0.5658464951,"remaining_time":0.5160779698},
{"learn":[3.861900081],"iteration":523,"passed_time":0.5667511821,"remaining_time":0.5148350433},
{"learn":[3.858502887],"iteration":524,"passed_time":0.567457547,"remaining_time":0.5134139711},
{"learn":[3.858335097],"iteration":525,"passed_time":0.5681694556,"remaining_time":0.512000612},
{"learn":[3.855719306],"iteration":526,"passed_time":0.5689370355,"remaining_time":0.510639882},
{"learn":[3.855137428],"iteration":527,"passed_time":0.5697261655,"remaining_time":0.5093006631},
{"learn":[3.851985706],"iteration":528,"passed_time":0.5703861033,"remaining_time":0.5078484965},
{"learn":[3.851051809],"iteration":529,"passed_time":0.5710739308,"remaining_time":0.5064240519},
{"learn":[3.850679146],"iteration":530,"passed_time":0.5718314012,"remaining_time":0.505063893},
{"learn":[3.848179484],"iteration":531,"passed_time":0.5725028402,"remaining_time":0.5036303181},
{"learn":[3.844551071],"iteration":532,"passed_time":0.5733206717,"remaining_time":0.5023278681},
{"learn":[3.841604794],"iteration":533,"passed_time":0.5751323079,"remaining_time":0.5018944859},
{"learn":[3.83969656],"iteration":534,"passed_time":0.5760596414,"remaining_time":0.5006873519},
{"learn":[3.836811463],"iteration":535,"passed_time":0.5768721827,"remaining_time":0.4993818895},
{"learn":[3.834182551],"iteration":536,"passed_time":0.5777183397,"remaining_time":0.4981072464},
{"learn":[3.828012842],"iteration":537,"passed_time":0.5785436839,"remaining_time":0.4968163233},
{"learn":[3.826636176],"iteration":538,"passed_time":0.5793606923,"remaining_time":0.4955199984},
{"learn":[3.826189798],"iteration":539,"passed_time":0.5801787572,"remaining_time":0.4942263487},
{"learn":[3.824104738],"iteration":540,"passed_time":0.5809276117,"remaining_time":0.4928757371},
{"learn":[3.82300218],"iteration":541,"passed_time":0.5815330698,"remaining_time":0.4914061734},
{"learn":[3.817146402],"iteration":542,"passed_time":0.5822081769,"remaining_time":0.4899984104},
{"learn":[3.814638044],"iteration":543,"passed_time":0.5828394221,"remaining_time":0.4885565744},
{"learn":[3.812979573],"iteration":544,"passed_time":0.5834822944,"remaining_time":0.4871274201},
{"learn":[3.811938825],"iteration":545,"passed_time":0.5841081254,"remaining_time":0.4856869761},
{"learn":[3.811479418],"iteration":546,"passed_time":0.5847291568,"remaining_time":0.4842455357},
{"learn":[3.80742981],"iteration":547,"passed_time":0.5853594963,"remaining_time":0.482814767},
{"learn":[3.805097043],"iteration":548,"passed_time":0.5860402138,"remaining_time":0.4814282995},
{"learn":[3.801577232],"iteration":549,"passed_time":0.5866854,"remaining_time":0.4800153273},
{"learn":[3.799762083],"iteration":550,"passed_time":0.5873413999,"remaining_time":0.4786139538},
{"learn":[3.796393455],"iteration":551,"passed_time":0.5879962144,"remaining_time":0.4772143189},
{"learn":[3.793486459],"iteration":552,"passed_time":0.5887271042,"remaining_time":0.4758788708},
{"learn":[3.792006091],"iteration":553,"passed_time":0.589497714,"remaining_time":0.474577582},
{"learn":[3.78932128],"iteration":554,"passed_time":0.5905417709,"remaining_time":0.4734974559},
{"learn":[3.787581812],"iteration":555,"passed_time":0.5913612096,"remaining_time":0.4722380882},
{"learn":[3.785308865],"iteration":556,"passed_time":0.5922106936,"remaining_time":0.4710041962},
{"learn":[3.78465475],"iteration":557,"passed_time":0.5929504709,"remaining_time":0.4696847816},
{"learn":[3.780498869],"iteration":558,"passed_time":0.5936305246,"remaining_time":0.4683203244},
{"learn":[3.778734909],"iteration":559,"passed_time":0.5942906661,"remaining_time":0.4669426662},
{"learn":[3.778652349],"iteration":560,"passed_time":0.5949141924,"remaining_time":0.4655389135},
{"learn":[3.777928006],"iteration":561,"passed_time":0.5955692531,"remaining_time":0.464162514},
{"learn":[3.776131406],"iteration":562,"passed_time":0.5961852051,"remaining_time":0.4627583209},
{"learn":[3.772925617],"iteration":563,"passed_time":0.5968445452,"remaining_time":0.461390464},
{"learn":[3.7727745],"iteration":564,"passed_time":0.5974531677,"remaining_time":0.4599860672},
{"learn":[3.771763073],"iteration":565,"passed_time":0.5980713356,"remaining_time":0.4585918015},
{"learn":[3.768738162],"iteration":566,"passed_time":0.598773228,"remaining_time":0.4572642112},
{"learn":[3.767220794],"iteration":567,"passed_time":0.5994417738,"remaining_time":0.4559134618},
{"learn":[3.766691102],"iteration":568,"passed_time":0.6001025748,"remaining_time":0.4545592438},
{"learn":[3.766259335],"iteration":569,"passed_time":0.6007290445,"remaining_time":0.4531815599},
{"learn":[3.76116362],"iteration":570,"passed_time":0.6013676288,"remaining_time":0.4518156091},
{"learn":[3.758633056],"iteration":571,"passed_time":0.6019798224,"remaining_time":0.4504324545},
{"learn":[3.754603809],"iteration":572,"passed_time":0.6026588164,"remaining_time":0.4491017707},
{"learn":[3.754070549],"iteration":573,"passed_time":0.6033133336,"remaining_time":0.4477551919},
{"learn":[3.750534319],"iteration":574,"passed_time":0.604132282,"remaining_time":0.4465325563},
{"learn":[3.746491516],"iteration":575,"passed_time":0.6051707229,"remaining_time":0.4454728932},
{"learn":[3.744210544],"iteration":576,"passed_time":0.6060412346,"remaining_time":0.4442901945},
{"learn":[3.742929991],"iteration":577,"passed_time":0.6067659532,"remaining_time":0.4430021319},
{"learn":[3.740402992],"iteration":578,"passed_time":0.6074668501,"remaining_time":0.4416986941},
{"learn":[3.739644243],"iteration":579,"passed_time":0.6080843939,"remaining_time":0.4403369749},
{"learn":[3.737529404],"iteration":580,"passed_time":0.6087360576,"remaining_time":0.4390024237},
{"learn":[3.737196923],"iteration":581,"passed_time":0.6093330315,"remaining_time":0.4376309402},
{"learn":[3.733954464],"iteration":582,"passed_time":0.6099601372,"remaining_time":0.4362836659},
{"learn":[3.731608623],"iteration":583,"passed_time":0.610579423,"remaining_time":0.4349332876},
{"learn":[3.729843952],"iteration":584,"passed_time":0.6112793836,"remaining_time":0.4336426397},
{"learn":[3.727223798],"iteration":585,"passed_time":0.6119352496,"remaining_time":0.4323228556},
{"learn":[3.725351667],"iteration":586,"passed_time":0.6126831511,"remaining_time":0.4310700876},
{"learn":[3.725026912],"iteration":587,"passed_time":0.6134161747,"remaining_time":0.4298086122},
{"learn":[3.721974565],"iteration":588,"passed_time":0.6140930599,"remaining_time":0.4285097583},
{"learn":[3.720269493],"iteration":589,"passed_time":0.6147493962,"remaining_time":0.427198733},
{"learn":[3.718907466],"iteration":590,"passed_time":0.615445486,"remaining_time":0.4259174345},
{"learn":[3.715602912],"iteration":591,"passed_time":0.6161623997,"remaining_time":0.4246524647},
{"learn":[3.714463059],"iteration":592,"passed_time":0.6168170918,"remaining_time":0.4233466381},
{"learn":[3.710802077],"iteration":593,"passed_time":0.6174570895,"remaining_time":0.4220329602},
{"learn":[3.708032435],"iteration":594,"passed_time":0.618209974,"remaining_time":0.4207983857},
{"learn":[3.703788939],"iteration":595,"passed_time":0.6192343656,"remaining_time":0.4197494693},
{"learn":[3.702500944],"iteration":596,"passed_time":0.6201184124,"remaining_time":0.4186058965},
{"learn":[3.698196925],"iteration":597,"passed_time":0.6208777897,"remaining_time":0.4173793837},
{"learn":[3.69658891],"iteration":598,"passed_time":0.6215491729,"remaining_time":0.4160955231},
{"learn":[3.696124066],"iteration":599,"passed_time":0.6221702133,"remaining_time":0.4147801422},
{"learn":[3.693537052],"iteration":600,"passed_time":0.6227694837,"remaining_time":0.413452619},
{"learn":[3.691343275],"iteration":601,"passed_time":0.6234128095,"remaining_time":0.4121566415},
{"learn":[3.690973831],"iteration":602,"passed_time":0.6240341492,"remaining_time":0.4108483536},
{"learn":[3.686151073],"iteration":603,"passed_time":0.6246709615,"remaining_time":0.4095524847},
{"learn":[3.683921982],"iteration":604,"passed_time":0.625336469,"remaining_time":0.4082775293},
{"learn":[3.679975271],"iteration":605,"passed_time":0.6259394354,"remaining_time":0.4069639233},
{"learn":[3.674047638],"iteration":606,"passed_time":0.6267050553,"remaining_time":0.4057579683},
{"learn":[3.673151794],"iteration":607,"passed_time":0.6273594016,"remaining_time":0.4044817195},
{"learn":[3.670953108],"iteration":608,"passed_time":0.6280149651,"remaining_time":0.4032082945},
{"learn":[3.6703947],"iteration":609,"passed_time":0.6286582431,"remaining_time":0.4019290407},
{"learn":[3.668433805],"iteration":610,"passed_time":0.6293203015,"remaining_time":0.4006638253},
{"learn":[3.668304956],"iteration":611,"passed_time":0.6299655413,"remaining_time":0.3993899183},
{"learn":[3.667880012],"iteration":612,"passed_time":0.6305860114,"remaining_time":0.3981024248},
{"learn":[3.667282264],"iteration":613,"passed_time":0.631186201,"remaining_time":0.3968043544},
{"learn":[3.664611483],"iteration":614,"passed_time":0.6318209341,"remaining_time":0.3955301783},
{"learn":[3.662543394],"iteration":615,"passed_time":0.6324736333,"remaining_time":0.3942692779},
{"learn":[3.659041959],"iteration":616,"passed_time":0.6332930303,"remaining_time":0.3931138259},
{"learn":[3.656868545],"iteration":617,"passed_time":0.6345098888,"remaining_time":0.3922051416},
{"learn":[3.654785614],"iteration":618,"passed_time":0.6352671055,"remaining_time":0.391012548},
{"learn":[3.654566096],"iteration":619,"passed_time":0.6361016828,"remaining_time":0.3898687733},
{"learn":[3.651007045],"iteration":620,"passed_time":0.6368071004,"remaining_time":0.3886471675},
{"learn":[3.648921786],"iteration":621,"passed_time":0.6374553464,"remaining_time":0.3873924774},
{"learn":[3.647655706],"iteration":622,"passed_time":0.6381117944,"remaining_time":0.3861446974},
{"learn":[3.647241144],"iteration":623,"passed_time":0.63873819,"remaining_time":0.3848807042},
{"learn":[3.644195689],"iteration":624,"passed_time":0.6394391758,"remaining_time":0.3836635055},
{"learn":[3.642632246],"iteration":625,"passed_time":0.6400606089,"remaining_time":0.3824004277},
{"learn":[3.642523322],"iteration":626,"passed_time":0.6405786815,"remaining_time":0.3810779078},
{"learn":[3.641494659],"iteration":627,"passed_time":0.6412192522,"remaining_time":0.3798305125},
{"learn":[3.63976496],"iteration":628,"passed_time":0.641869601,"remaining_time":0.378590814},
{"learn":[3.637945652],"iteration":629,"passed_time":0.6425152508,"remaining_time":0.3773502267},
{"learn":[3.636233667],"iteration":630,"passed_time":0.6431226583,"remaining_time":0.3760891615},
{"learn":[3.635304404],"iteration":631,"passed_time":0.6437235552,"remaining_time":0.3748263739},
{"learn":[3.632234951],"iteration":632,"passed_time":0.6443727579,"remaining_time":0.3735936843},
{"learn":[3.631630987],"iteration":633,"passed_time":0.6449953097,"remaining_time":0.3723474501},
{"learn":[3.630301009],"iteration":634,"passed_time":0.6456483083,"remaining_time":0.3711206811},
{"learn":[3.629077964],"iteration":635,"passed_time":0.6462835877,"remaining_time":0.3698855753},
{"learn":[3.628004522],"iteration":636,"passed_time":0.6469010658,"remaining_time":0.3686422086},
{"learn":[3.625062876],"iteration":637,"passed_time":0.6475274953,"remaining_time":0.3674058829},
{"learn":[3.624917986],"iteration":638,"passed_time":0.6483199313,"remaining_time":0.3662652507},
{"learn":[3.622887087],"iteration":639,"passed_time":0.6493866098,"remaining_time":0.365279968},
{"learn":[3.621220865],"iteration":640,"passed_time":0.6501538768,"remaining_time":0.3641267422},
{"learn":[3.621143844],"iteration":641,"passed_time":0.6508476676,"remaining_time":0.3629337461},
{"learn":[3.620822821],"iteration":642,"passed_time":0.6514453502,"remaining_time":0.3616889425},
{"learn":[3.619202826],"iteration":643,"passed_time":0.6520602024,"remaining_time":0.3604556399},
{"learn":[3.618204882],"iteration":644,"passed_time":0.6526972139,"remaining_time":0.359236451},
{"learn":[3.614259666],"iteration":645,"passed_time":0.6533575695,"remaining_time":0.358031857},
{"learn":[3.613415661],"iteration":646,"passed_time":0.6540121945,"remaining_time":0.3568258186},
{"learn":[3.611096773],"iteration":647,"passed_time":0.654609821,"remaining_time":0.3555905201},
{"learn":[3.610820695],"iteration":648,"passed_time":0.6552483536,"remaining_time":0.3543793099},
{"learn":[3.609290065],"iteration":649,"passed_time":0.6558908294,"remaining_time":0.3531719851},
{"learn":[3.60897947],"iteration":650,"passed_time":0.6565460575,"remaining_time":0.351973232},
{"learn":[3.606570702],"iteration":651,"passed_time":0.6571568152,"remaining_time":0.3507524106},
{"learn":[3.606292637],"iteration":652,"passed_time":0.6578066198,"remaining_time":0.3495542069},
{"learn":[3.602753838],"iteration":653,"passed_time":0.6584862219,"remaining_time":0.3483734446},
{"learn":[3.599755869],"iteration":654,"passed_time":0.6591329204,"remaining_time":0.3471768817},
{"learn":[3.599509575],"iteration":655,"passed_time":0.659778487,"remaining_time":0.3459814017},
{"learn":[3.595337722],"iteration":656,"passed_time":0.660432696,"remaining_time":0.3447921076},
{"learn":[3.595168561],"iteration":657,"passed_time":0.661054811,"remaining_time":0.3435877589},
{"learn":[3.59290559],"iteration":658,"passed_time":0.6617252141,"remaining_time":0.3424101639},
{"learn":[3.592015928],"iteration":659,"passed_time":0.6623879012,"remaining_time":0.3412301309},
{"learn":[3.590680403],"iteration":660,"passed_time":0.6631466351,"remaining_time":0.3401009218},
{"learn":[3.590361532],"iteration":661,"passed_time":0.6641066363,"remaining_time":0.3390755938},
{"learn":[3.589069739],"iteration":662,"passed_time":0.6648963879,"remaining_time":0.3379639257},
{"learn":[3.585010186],"iteration":663,"passed_time":0.6655880217,"remaining_time":0.3368035772},
{"learn":[3.582997552],"iteration":664,"passed_time":0.666289506,"remaining_time":0.3356496007},
{"learn":[3.582119256],"iteration":665,"passed_time":0.6669550041,"remaining_time":0.334478936},
{"learn":[3.579019356],"iteration":666,"passed_time":0.6676003388,"remaining_time":0.3332997194},
{"learn":[3.57719559],"iteration":667,"passed_time":0.6682175212,"remaining_time":0.3321081093},
{"learn":[3.574050046],"iteration":668,"passed_time":0.6688515214,"remaining_time":0.3309265375},
{"learn":[3.572204518],"iteration":669,"passed_time":0.6695241046,"remaining_time":0.3297656038},
{"learn":[3.569508025],"iteration":670,"passed_time":0.6701127917,"remaining_time":0.3285649902},
{"learn":[3.566268704],"iteration":671,"passed_time":0.6707233099,"remaining_time":0.3273768537},
{"learn":[3.562564052],"iteration":672,"passed_time":0.6713789465,"remaining_time":0.3262123559},
{"learn":[3.561173586],"iteration":673,"passed_time":0.6720048629,"remaining_time":0.325034993},
{"learn":[3.559551904],"iteration":674,"passed_time":0.6726776181,"remaining_time":0.3238818161},
{"learn":[3.558593054],"iteration":675,"passed_time":0.6732711341,"remaining_time":0.322692082},
{"learn":[3.555647008],"iteration":676,"passed_time":0.6739189048,"remaining_time":0.3215299945},
{"learn":[3.553100059],"iteration":677,"passed_time":0.6745785239,"remaining_time":0.3203750512},
{"learn":[3.55085578],"iteration":678,"passed_time":0.6752277959,"remaining_time":0.3192166752},
{"learn":[3.550737965],"iteration":679,"passed_time":0.6758513846,"remaining_time":0.3180477104},
{"learn":[3.549408772],"iteration":680,"passed_time":0.6765035639,"remaining_time":0.3168937399},
{"learn":[3.547390589],"iteration":681,"passed_time":0.6771692002,"remaining_time":0.3157475156},
{"learn":[3.54723575],"iteration":682,"passed_time":0.6779426057,"remaining_time":0.3146527174},
{"learn":[3.543988891],"iteration":683,"passed_time":0.6791084657,"remaining_time":0.3137401684},
{"learn":[3.543868508],"iteration":684,"passed_time":0.6799632176,"remaining_time":0.3126838154},
{"learn":[3.542752124],"iteration":685,"passed_time":0.6806478826,"remaining_time":0.311550197},
{"learn":[3.541334315],"iteration":686,"passed_time":0.6813912705,"remaining_time":0.31044464},
{"learn":[3.540208266],"iteration":687,"passed_time":0.6820584875,"remaining_time":0.3093055932},
{"learn":[3.537730983],"iteration":688,"passed_time":0.6827559329,"remaining_time":0.3081815604},
{"learn":[3.53419867],"iteration":689,"passed_time":0.6833872994,"remaining_time":0.3070290765},
{"learn":[3.532628335],"iteration":690,"passed_time":0.6840355322,"remaining_time":0.3058856432},
{"learn":[3.532204987],"iteration":691,"passed_time":0.6847018536,"remaining_time":0.304751692},
{"learn":[3.530618147],"iteration":692,"passed_time":0.6853575155,"remaining_time":0.3036143683},
{"learn":[3.528909306],"iteration":693,"passed_time":0.6859981498,"remaining_time":0.3024718067},
{"learn":[3.526700678],"iteration":694,"passed_time":0.6866405764,"remaining_time":0.301331476},
{"learn":[3.526439574],"iteration":695,"passed_time":0.6872431043,"remaining_time":0.300175149},
{"learn":[3.525784216],"iteration":696,"passed_time":0.6878863294,"remaining_time":0.299038103},
{"learn":[3.524112693],"iteration":697,"passed_time":0.6885114968,"remaining_time":0.2978946591},
{"learn":[3.522813541],"iteration":698,"passed_time":0.6891751602,"remaining_time":0.296769275},
{"learn":[3.519148203],"iteration":699,"passed_time":0.6898273395,"remaining_time":0.2956402883},
{"learn":[3.517236747],"iteration":700,"passed_time":0.690455208,"remaining_time":0.2945022927},
{"learn":[3.515603888],"iteration":701,"passed_time":0.6910941941,"remaining_time":0.2933704699},
{"learn":[3.51263524],"iteration":702,"passed_time":0.6917522025,"remaining_time":0.2922480856},
{"learn":[3.51123442],"iteration":703,"passed_time":0.6925119812,"remaining_time":0.2911698103},
{"learn":[3.50828027],"iteration":704,"passed_time":0.6932667797,"remaining_time":0.2900903546},
{"learn":[3.508265537],"iteration":705,"passed_time":0.6938896919,"remaining_time":0.2889568972},
{"learn":[3.506774876],"iteration":706,"passed_time":0.6948444317,"remaining_time":0.2879624024},
{"learn":[3.50552068],"iteration":707,"passed_time":0.695714769,"remaining_time":0.2869332098},
{"learn":[3.501973993],"iteration":708,"passed_time":0.6965265613,"remaining_time":0.2858804363},
{"learn":[3.498880354],"iteration":709,"passed_time":0.697254807,"remaining_time":0.284794217},
{"learn":[3.497370959],"iteration":710,"passed_time":0.6979236001,"remaining_time":0.2836848389},
{"learn":[3.496050455],"iteration":711,"passed_time":0.6985729541,"remaining_time":0.2825688354},
{"learn":[3.495630067],"iteration":712,"passed_time":0.6992094032,"remaining_time":0.2814489463},
{"learn":[3.49550669],"iteration":713,"passed_time":0.6999026006,"remaining_time":0.2803531425},
{"learn":[3.493652375],"iteration":714,"passed_time":0.7005758893,"remaining_time":0.2792505293},
{"learn":[3.491915684],"iteration":715,"passed_time":0.7012449093,"remaining_time":0.2781474221},
{"learn":[3.490303956],"iteration":716,"passed_time":0.7018989512,"remaining_time":0.2770396139},
{"learn":[3.488363853],"iteration":717,"passed_time":0.7025561704,"remaining_time":0.2759343176},
{"learn":[3.485483936],"iteration":718,"passed_time":0.7032232364,"remaining_time":0.274834116},
{"learn":[3.483763466],"iteration":719,"passed_time":0.7038599534,"remaining_time":0.2737233152},
{"learn":[3.481642352],"iteration":720,"passed_time":0.7046561382,"remaining_time":0.2726755375},
{"learn":[3.479826119],"iteration":721,"passed_time":0.7053411733,"remaining_time":0.2715856595},
{"learn":[3.478588728],"iteration":722,"passed_time":0.7060336877,"remaining_time":0.2704997669},
{"learn":[3.475390887],"iteration":723,"passed_time":0.7066949632,"remaining_time":0.2694030523},
{"learn":[3.472636852],"iteration":724,"passed_time":0.7074430941,"remaining_time":0.268340484},
{"learn":[3.47061883],"iteration":725,"passed_time":0.7081514155,"remaining_time":0.2672637573},
{"learn":[3.46953149],"iteration":726,"passed_time":0.7088191937,"remaining_time":0.2661728197},
{"learn":[3.467217162],"iteration":727,"passed_time":0.7094959836,"remaining_time":0.2650864115},
{"learn":[3.465686216],"iteration":728,"passed_time":0.7101645508,"remaining_time":0.2639980703},
{"learn":[3.462631216],"iteration":729,"passed_time":0.7108009767,"remaining_time":0.2628989914},
{"learn":[3.461451053],"iteration":730,"passed_time":0.711432898,"remaining_time":0.2617995206},
{"learn":[3.458950469],"iteration":731,"passed_time":0.7121099341,"remaining_time":0.2607178447},
{"learn":[3.458072145],"iteration":732,"passed_time":0.7127472902,"remaining_time":0.2596228192},
{"learn":[3.454364268],"iteration":733,"passed_time":0.7134064362,"remaining_time":0.2585369374},
{"learn":[3.453243406],"iteration":734,"passed_time":0.7140915882,"remaining_time":0.257461593},
{"learn":[3.453017963],"iteration":735,"passed_time":0.7147331763,"remaining_time":0.2563716828},
{"learn":[3.45201581],"iteration":736,"passed_time":0.715392597,"remaining_time":0.2552893528},
{"learn":[3.449510107],"iteration":737,"passed_time":0.7160394151,"remaining_time":0.2542036948},
{"learn":[3.447189189],"iteration":738,"passed_time":0.7166712986,"remaining_time":0.2531139498},
{"learn":[3.446423605],"iteration":739,"passed_time":0.7173257648,"remaining_time":0.2520333768},
{"learn":[3.445531987],"iteration":740,"passed_time":0.7180069054,"remaining_time":0.2509632773},
{"learn":[3.445328199],"iteration":741,"passed_time":0.7186249516,"remaining_time":0.2498722878},
{"learn":[3.443327544],"iteration":742,"passed_time":0.719322291,"remaining_time":0.2488099984},
{"learn":[3.441475798],"iteration":743,"passed_time":0.7201050478,"remaining_time":0.247778081},
{"learn":[3.439046501],"iteration":744,"passed_time":0.7207822095,"remaining_time":0.2467106892},
{"learn":[3.435899469],"iteration":745,"passed_time":0.7214403642,"remaining_time":0.245637872},
{"learn":[3.433988352],"iteration":746,"passed_time":0.7221137364,"remaining_time":0.244571319},
{"learn":[3.433413263],"iteration":747,"passed_time":0.7227698551,"remaining_time":0.2435000047},
{"learn":[3.429944699],"iteration":748,"passed_time":0.7234644955,"remaining_time":0.2424427081},
{"learn":[3.429291634],"iteration":749,"passed_time":0.724082289,"remaining_time":0.241360763},
{"learn":[3.429175603],"iteration":750,"passed_time":0.7247392202,"remaining_time":0.2402930304},
{"learn":[3.428780323],"iteration":751,"passed_time":0.7253424935,"remaining_time":0.2392086947},
{"learn":[3.423893341],"iteration":752,"passed_time":0.7259937968,"remaining_time":0.2381413915},
{"learn":[3.421024316],"iteration":753,"passed_time":0.7266567904,"remaining_time":0.2370790059},
{"learn":[3.420969872],"iteration":754,"passed_time":0.7273073562,"remaining_time":0.2360136454},
{"learn":[3.419544785],"iteration":755,"passed_time":0.7279356864,"remaining_time":0.2349422057},
{"learn":[3.417057977],"iteration":756,"passed_time":0.7286320617,"remaining_time":0.2338937794},
{"learn":[3.415160245],"iteration":757,"passed_time":0.7292551149,"remaining_time":0.2328228731},
{"learn":[3.412854597],"iteration":758,"passed_time":0.7298927507,"remaining_time":0.2317577772},
{"learn":[3.410926347],"iteration":759,"passed_time":0.7305365493,"remaining_time":0.2306957524},
{"learn":[3.408963843],"iteration":760,"passed_time":0.7311746223,"remaining_time":0.2296330286},
{"learn":[3.407629634],"iteration":761,"passed_time":0.7318294878,"remaining_time":0.2285766642},
{"learn":[3.404384724],"iteration":762,"passed_time":0.7324821471,"remaining_time":0.2275206669},
{"learn":[3.403041656],"iteration":763,"passed_time":0.73312791,"remaining_time":0.2264635952},
{"learn":[3.401101731],"iteration":764,"passed_time":0.7339268616,"remaining_time":0.2254546568},
{"learn":[3.400890668],"iteration":765,"passed_time":0.7348273741,"remaining_time":0.2244772918},
{"learn":[3.399289941],"iteration":766,"passed_time":0.7358116693,"remaining_time":0.2235255788},
{"learn":[3.399202366],"iteration":767,"passed_time":0.7367487962,"remaining_time":0.2225595322},
{"learn":[3.397447845],"iteration":768,"passed_time":0.7376051527,"remaining_time":0.2215692981},
{"learn":[3.394655341],"iteration":769,"passed_time":0.738263874,"remaining_time":0.220520378},
{"learn":[3.393228229],"iteration":770,"passed_time":0.7389014457,"remaining_time":0.2194661881},
{"learn":[3.389691197],"iteration":771,"passed_time":0.7395600075,"remaining_time":0.2184192768},
{"learn":[3.389626772],"iteration":772,"passed_time":0.7401733151,"remaining_time":0.2173600809},
{"learn":[3.388480222],"iteration":773,"passed_time":0.7408288222,"remaining_time":0.2163143589},
{"learn":[3.388215066],"iteration":774,"passed_time":0.7414861048,"remaining_time":0.2152701595},
{"learn":[3.386324358],"iteration":775,"passed_time":0.742167279,"remaining_time":0.2142338537},
{"learn":[3.383913061],"iteration":776,"passed_time":0.7428357131,"remaining_time":0.2131948057},
{"learn":[3.382839768],"iteration":777,"passed_time":0.743494134,"remaining_time":0.2121538531},
{"learn":[3.381961844],"iteration":778,"passed_time":0.7441557645,"remaining_time":0.2111147933},
{"learn":[3.381521703],"iteration":779,"passed_time":0.7448154336,"remaining_time":0.2100761479},
{"learn":[3.380918963],"iteration":780,"passed_time":0.7454356593,"remaining_time":0.2090274128},
{"learn":[3.377139006],"iteration":781,"passed_time":0.7460883896,"remaining_time":0.2079888349},
{"learn":[3.376004372],"iteration":782,"passed_time":0.7467497814,"remaining_time":0.2069536431},
{"learn":[3.373826468],"iteration":783,"passed_time":0.7473540092,"remaining_time":0.2059036556},
{"learn":[3.373546786],"iteration":784,"passed_time":0.7479756658,"remaining_time":0.2048595772},
{"learn":[3.372109181],"iteration":785,"passed_time":0.7486172806,"remaining_time":0.2038220077},
{"learn":[3.370764924],"iteration":786,"passed_time":0.7492711224,"remaining_time":0.2027887536},
{"learn":[3.367833107],"iteration":787,"passed_time":0.7499231019,"remaining_time":0.2017559614},
{"learn":[3.36450404],"iteration":788,"passed_time":0.7505866564,"remaining_time":0.20072723},
{"learn":[3.361794558],"iteration":789,"passed_time":0.7512343683,"remaining_time":0.1996952118},
{"learn":[3.356880529],"iteration":790,"passed_time":0.7518923617,"remaining_time":0.1986668819},
{"learn":[3.353843509],"iteration":791,"passed_time":0.7525649296,"remaining_time":0.1976433149},
{"learn":[3.353640253],"iteration":792,"passed_time":0.7531958568,"remaining_time":0.1966097634},
{"learn":[3.353055088],"iteration":793,"passed_time":0.7537970342,"remaining_time":0.1955695076},
{"learn":[3.351415617],"iteration":794,"passed_time":0.7544405366,"remaining_time":0.1945412704},
{"learn":[3.349169061],"iteration":795,"passed_time":0.7550926292,"remaining_time":0.1935162015},
{"learn":[3.346211014],"iteration":796,"passed_time":0.7557513941,"remaining_time":0.1924937679},
{"learn":[3.344560452],"iteration":797,"passed_time":0.7564345897,"remaining_time":0.19147843},
{"learn":[3.344445461],"iteration":798,"passed_time":0.7570464439,"remaining_time":0.1904459765},
{"learn":[3.342608898],"iteration":799,"passed_time":0.7577128727,"remaining_time":0.1894282182},
{"learn":[3.339572899],"iteration":800,"passed_time":0.7583583615,"remaining_time":0.1884061348},
{"learn":[3.339309302],"iteration":801,"passed_time":0.7589799128,"remaining_time":0.1873790807},
{"learn":[3.33698088],"iteration":802,"passed_time":0.7596201114,"remaining_time":0.1863576114},
{"learn":[3.334746342],"iteration":803,"passed_time":0.7602679999,"remaining_time":0.1853389652},
{"learn":[3.332048511],"iteration":804,"passed_time":0.7609330182,"remaining_time":0.1843253895},
{"learn":[3.331932544],"iteration":805,"passed_time":0.761559813,"remaining_time":0.1833034786},
{"learn":[3.330541133],"iteration":806,"passed_time":0.7621839798,"remaining_time":0.1822819183},
{"learn":[3.329124989],"iteration":807,"passed_time":0.762839307,"remaining_time":0.1812687462},
{"learn":[3.32583918],"iteration":808,"passed_time":0.7635112858,"remaining_time":0.1802603901},
{"learn":[3.325287299],"iteration":809,"passed_time":0.7641402919,"remaining_time":0.1792427845},
{"learn":[3.322745162],"iteration":810,"passed_time":0.7647865326,"remaining_time":0.1782301537},
{"learn":[3.319733662],"iteration":811,"passed_time":0.7653926826,"remaining_time":0.1772091433},
{"learn":[3.318080007],"iteration":812,"passed_time":0.7660527688,"remaining_time":0.1762015594},
{"learn":[3.317179538],"iteration":813,"passed_time":0.7666933339,"remaining_time":0.1751903687},
{"learn":[3.315685949],"iteration":814,"passed_time":0.7673395185,"remaining_time":0.1741813631},
{"learn":[3.314944576],"iteration":815,"passed_time":0.7679717742,"remaining_time":0.173170106},
{"learn":[3.312369052],"iteration":816,"passed_time":0.7686176131,"remaining_time":0.1721628191},
{"learn":[3.312321621],"iteration":817,"passed_time":0.7690868285,"remaining_time":0.1711171183},
{"learn":[3.309465776],"iteration":818,"passed_time":0.7697404476,"remaining_time":0.1701135788},
{"learn":[3.308307377],"iteration":819,"passed_time":0.7705327084,"remaining_time":0.1691413262},
{"learn":[3.308076804],"iteration":820,"passed_time":0.7712250848,"remaining_time":0.1681477347},
{"learn":[3.305643326],"iteration":821,"passed_time":0.7719191681,"remaining_time":0.1671552457},
{"learn":[3.304154814],"iteration":822,"passed_time":0.7726663798,"remaining_time":0.1661749079},
{"learn":[3.303076321],"iteration":823,"passed_time":0.7733936418,"remaining_time":0.165190875},
{"learn":[3.301746372],"iteration":824,"passed_time":0.7740761356,"remaining_time":0.1641979681},
{"learn":[3.301345455],"iteration":825,"passed_time":0.7747160044,"remaining_time":0.1631968339},
{"learn":[3.299181039],"iteration":826,"passed_time":0.7753505898,"remaining_time":0.162195468},
{"learn":[3.297989357],"iteration":827,"passed_time":0.7760185568,"remaining_time":0.1612019224},
{"learn":[3.294775182],"iteration":828,"passed_time":0.7766675579,"remaining_time":0.1602052502},
{"learn":[3.293840636],"iteration":829,"passed_time":0.777332386,"remaining_time":0.1592126574},
{"learn":[3.289279397],"iteration":830,"passed_time":0.7779865328,"remaining_time":0.1582186812},
{"learn":[3.286204979],"iteration":831,"passed_time":0.7786380453,"remaining_time":0.1572249899},
{"learn":[3.284833593],"iteration":832,"passed_time":0.7793011648,"remaining_time":0.1562344472},
{"learn":[3.283519914],"iteration":833,"passed_time":0.7799274226,"remaining_time":0.1552373527},
{"learn":[3.282853026],"iteration":834,"passed_time":0.7805813272,"remaining_time":0.1542466096},
{"learn":[3.281944673],"iteration":835,"passed_time":0.781207884,"remaining_time":0.1532513074},
{"learn":[3.279764865],"iteration":836,"passed_time":0.7818401625,"remaining_time":0.1522580006},
{"learn":[3.277468839],"iteration":837,"passed_time":0.7824733335,"remaining_time":0.1512657279},
{"learn":[3.277124974],"iteration":838,"passed_time":0.7831299192,"remaining_time":0.1502788045},
{"learn":[3.275636037],"iteration":839,"passed_time":0.7838220211,"remaining_time":0.1492994326},
{"learn":[3.274413635],"iteration":840,"passed_time":0.7855160144,"remaining_time":0.1485101621},
{"learn":[3.272636087],"iteration":841,"passed_time":0.7861537313,"remaining_time":0.1475205339},
{"learn":[3.269644466],"iteration":842,"passed_time":0.7868289186,"remaining_time":0.1465387191},
{"learn":[3.26852083],"iteration":843,"passed_time":0.7874704125,"remaining_time":0.1455514033},
{"learn":[3.267820927],"iteration":844,"passed_time":0.788135258,"remaining_time":0.1445691893},
{"learn":[3.267331099],"iteration":845,"passed_time":0.7887776479,"remaining_time":0.143583638},
{"learn":[3.267231014],"iteration":846,"passed_time":0.7894037233,"remaining_time":0.14259595},
{"learn":[3.267158695],"iteration":847,"passed_time":0.7900569093,"remaining_time":0.1416139743},
{"learn":[3.264718705],"iteration":848,"passed_time":0.7906955667,"remaining_time":0.1406301891},
{"learn":[3.261678512],"iteration":849,"passed_time":0.7913352665,"remaining_time":0.1396474},
{"learn":[3.261368381],"iteration":850,"passed_time":0.7919745002,"remaining_time":0.1386653355},
{"learn":[3.260128799],"iteration":851,"passed_time":0.7926129282,"remaining_time":0.1376839359},
{"learn":[3.258972952],"iteration":852,"passed_time":0.7932809566,"remaining_time":0.1367084415},
{"learn":[3.258724846],"iteration":853,"passed_time":0.793912975,"remaining_time":0.1357275109},
{"learn":[3.25686724],"iteration":854,"passed_time":0.79459728,"remaining_time":0.1347562639},
{"learn":[3.255750259],"iteration":855,"passed_time":0.7952780028,"remaining_time":0.1337850846},
{"learn":[3.254915866],"iteration":856,"passed_time":0.795955274,"remaining_time":0.1328140072},
{"learn":[3.254348625],"iteration":857,"passed_time":0.7966099475,"remaining_time":0.1318398748},
{"learn":[3.253408514],"iteration":858,"passed_time":0.797237122,"remaining_time":0.1308619723},
{"learn":[3.253291714],"iteration":859,"passed_time":0.7978881516,"remaining_time":0.1298887689},
{"learn":[3.250186342],"iteration":860,"passed_time":0.798553232,"remaining_time":0.1289185822},
{"learn":[3.249141318],"iteration":861,"passed_time":0.7991630237,"remaining_time":0.1279402521},
{"learn":[3.246300388],"iteration":862,"passed_time":0.7998431146,"remaining_time":0.1269739359},
{"learn":[3.245205135],"iteration":863,"passed_time":0.8004803512,"remaining_time":0.1260015368},
{"learn":[3.244403535],"iteration":864,"passed_time":0.8011275592,"remaining_time":0.1250314688},
{"learn":[3.244211781],"iteration":865,"passed_time":0.8017433557,"remaining_time":0.124057286},
{"learn":[3.242286347],"iteration":866,"passed_time":0.8023992195,"remaining_time":0.1230900764},
{"learn":[3.239606746],"iteration":867,"passed_time":0.8030522449,"remaining_time":0.1221231525},
{"learn":[3.236773361],"iteration":868,"passed_time":0.8036588306,"remaining_time":0.1211499503},
{"learn":[3.234552446],"iteration":869,"passed_time":0.8042922053,"remaining_time":0.1201815939},
{"learn":[3.233724647],"iteration":870,"passed_time":0.8049542223,"remaining_time":0.1192182488},
{"learn":[3.230851485],"iteration":871,"passed_time":0.8056268519,"remaining_time":0.1182571526},
{"learn":[3.227728941],"iteration":872,"passed_time":0.806297007,"remaining_time":0.1172963573},
{"learn":[3.225787575],"iteration":873,"passed_time":0.8069556891,"remaining_time":0.116334573},
{"learn":[3.222797487],"iteration":874,"passed_time":0.8075901542,"remaining_time":0.115370022},
{"learn":[3.22137014],"iteration":875,"passed_time":0.8082504738,"remaining_time":0.1144098844},
{"learn":[3.219701963],"iteration":876,"passed_time":0.8089325515,"remaining_time":0.1134534821},
{"learn":[3.21783327],"iteration":877,"passed_time":0.8095891997,"remaining_time":0.1124941713},
{"learn":[3.217713355],"iteration":878,"passed_time":0.8101875445,"remaining_time":0.1115275232},
{"learn":[3.217666091],"iteration":879,"passed_time":0.8108114605,"remaining_time":0.1105651992},
{"learn":[3.214962005],"iteration":880,"passed_time":0.8114555727,"remaining_time":0.1096063713},
{"learn":[3.214081828],"iteration":881,"passed_time":0.8121150166,"remaining_time":0.1086503083},
{"learn":[3.213358337],"iteration":882,"passed_time":0.8127575603,"remaining_time":0.1076926779},
{"learn":[3.210850401],"iteration":883,"passed_time":0.8134849147,"remaining_time":0.1067468893},
{"learn":[3.207810328],"iteration":884,"passed_time":0.8141384542,"remaining_time":0.1057920025},
{"learn":[3.204935073],"iteration":885,"passed_time":0.8147904123,"remaining_time":0.1048375926},
{"learn":[3.20280198],"iteration":886,"passed_time":0.8154555187,"remaining_time":0.1038855396},
{"learn":[3.200663495],"iteration":887,"passed_time":0.816116994,"remaining_time":0.1029336749},
{"learn":[3.197301669],"iteration":888,"passed_time":0.8167720329,"remaining_time":0.1019816599},
{"learn":[3.195666943],"iteration":889,"passed_time":0.8174396613,"remaining_time":0.1010318683},
{"learn":[3.193886506],"iteration":890,"passed_time":0.8181350728,"remaining_time":0.1000861088},
{"learn":[3.190601248],"iteration":891,"passed_time":0.8187780218,"remaining_time":0.09913455869},
{"learn":[3.188983797],"iteration":892,"passed_time":0.8194231156,"remaining_time":0.09818395675},
{"learn":[3.187365749],"iteration":893,"passed_time":0.8200891341,"remaining_time":0.09723651925},
{"learn":[3.186160771],"iteration":894,"passed_time":0.8207067093,"remaining_time":0.09628402734},
{"learn":[3.185358981],"iteration":895,"passed_time":0.8213605949,"remaining_time":0.09533649762},
{"learn":[3.183832164],"iteration":896,"passed_time":0.8220186736,"remaining_time":0.09439010411},
{"learn":[3.183106966],"iteration":897,"passed_time":0.8226788637,"remaining_time":0.09344459253},
{"learn":[3.182838152],"iteration":898,"passed_time":0.8233401338,"remaining_time":0.09249983706},
{"learn":[3.180835453],"iteration":899,"passed_time":0.8240015699,"remaining_time":0.09155572999},
{"learn":[3.179957348],"iteration":900,"passed_time":0.824627706,"remaining_time":0.09060837169},
{"learn":[3.179752966],"iteration":901,"passed_time":0.8252951613,"remaining_time":0.08966621487},
{"learn":[3.178851983],"iteration":902,"passed_time":0.8259071826,"remaining_time":0.08871871175},
{"learn":[3.176748586],"iteration":903,"passed_time":0.8265557733,"remaining_time":0.08777583433},
{"learn":[3.172960988],"iteration":904,"passed_time":0.8272348979,"remaining_time":0.08683681249},
{"learn":[3.172794225],"iteration":905,"passed_time":0.8279246701,"remaining_time":0.08589946908},
{"learn":[3.169996507],"iteration":906,"passed_time":0.8285814796,"remaining_time":0.08495929173},
{"learn":[3.16813015],"iteration":907,"passed_time":0.82925051,"remaining_time":0.08402097678},
{"learn":[3.166920871],"iteration":908,"passed_time":0.8299253694,"remaining_time":0.08308383786},
{"learn":[3.16531606],"iteration":909,"passed_time":0.8305542367,"remaining_time":0.0821427267},
{"learn":[3.162035247],"iteration":910,"passed_time":0.8311665676,"remaining_time":0.08120068553},
{"learn":[3.16189467],"iteration":911,"passed_time":0.8317978056,"remaining_time":0.08026119177},
{"learn":[3.161008416],"iteration":912,"passed_time":0.8324470083,"remaining_time":0.07932408513},
{"learn":[3.160560787],"iteration":913,"passed_time":0.8330764918,"remaining_time":0.07838575306},
{"learn":[3.160416261],"iteration":914,"passed_time":0.8337191989,"remaining_time":0.07744932449},
{"learn":[3.15844291],"iteration":915,"passed_time":0.8343423912,"remaining_time":0.07651174767},
{"learn":[3.155040501],"iteration":916,"passed_time":0.8349495179,"remaining_time":0.07557340238},
{"learn":[3.154937548],"iteration":917,"passed_time":0.8355929539,"remaining_time":0.07463902203},
{"learn":[3.153721161],"iteration":918,"passed_time":0.8362166615,"remaining_time":0.073703536},
{"learn":[3.153170511],"iteration":919,"passed_time":0.8368587149,"remaining_time":0.07277032303},
{"learn":[3.153113601],"iteration":920,"passed_time":0.8375085898,"remaining_time":0.07183841324},
{"learn":[3.150607379],"iteration":921,"passed_time":0.8381312012,"remaining_time":0.07090480878},
{"learn":[3.148408359],"iteration":922,"passed_time":0.8387806651,"remaining_time":0.06997411833},
{"learn":[3.147495728],"iteration":923,"passed_time":0.8394265597,"remaining_time":0.06904374301},
{"learn":[3.146946235],"iteration":924,"passed_time":0.8400755512,"remaining_time":0.06811423388},
{"learn":[3.14472738],"iteration":925,"passed_time":0.840740411,"remaining_time":0.06718659872},
{"learn":[3.144469477],"iteration":926,"passed_time":0.8414180126,"remaining_time":0.06626053389},
{"learn":[3.142975516],"iteration":927,"passed_time":0.8420794715,"remaining_time":0.0653337521},
{"learn":[3.14079113],"iteration":928,"passed_time":0.84276779,"remaining_time":0.06440959429},
{"learn":[3.138173032],"iteration":929,"passed_time":0.843443381,"remaining_time":0.06348498567},
{"learn":[3.136352813],"iteration":930,"passed_time":0.8440767282,"remaining_time":0.06255778114},
{"learn":[3.133735004],"iteration":931,"passed_time":0.8447055244,"remaining_time":0.06163087517},
{"learn":[3.1319496],"iteration":932,"passed_time":0.8453691903,"remaining_time":0.06070711227},
{"learn":[3.129865343],"iteration":933,"passed_time":0.8461006343,"remaining_time":0.05978869578},
{"learn":[3.129830206],"iteration":934,"passed_time":0.8465983806,"remaining_time":0.05885443288},
{"learn":[3.126676562],"iteration":935,"passed_time":0.8472619395,"remaining_time":0.05793244031},
{"learn":[3.12645665],"iteration":936,"passed_time":0.8479062091,"remaining_time":0.05700970242},
{"learn":[3.126378007],"iteration":937,"passed_time":0.8485091131,"remaining_time":0.0560848241},
{"learn":[3.124621914],"iteration":938,"passed_time":0.8491302147,"remaining_time":0.05516181374},
{"learn":[3.123379018],"iteration":939,"passed_time":0.8497663334,"remaining_time":0.05424040426},
{"learn":[3.123332451],"iteration":940,"passed_time":0.850442036,"remaining_time":0.05332208302},
{"learn":[3.122432444],"iteration":941,"passed_time":0.8510853104,"remaining_time":0.05240228026},
{"learn":[3.121889006],"iteration":942,"passed_time":0.8517357056,"remaining_time":0.0514834944},
{"learn":[3.121070914],"iteration":943,"passed_time":0.8523544641,"remaining_time":0.05056340041},
{"learn":[3.118444705],"iteration":944,"passed_time":0.8530184796,"remaining_time":0.04964657818},
{"learn":[3.116820458],"iteration":945,"passed_time":0.8536902104,"remaining_time":0.04873073083},
{"learn":[3.114971041],"iteration":946,"passed_time":0.8543246599,"remaining_time":0.04781331254},
{"learn":[3.114685138],"iteration":947,"passed_time":0.8549818023,"remaining_time":0.04689773599},
{"learn":[3.113399363],"iteration":948,"passed_time":0.855897215,"remaining_time":0.04599658374},
{"learn":[3.110575399],"iteration":949,"passed_time":0.8566345898,"remaining_time":0.04508603104},
{"learn":[3.110466553],"iteration":950,"passed_time":0.8572942146,"remaining_time":0.0441718365},
{"learn":[3.108691641],"iteration":951,"passed_time":0.8579550102,"remaining_time":0.04325823581},
{"learn":[3.107898017],"iteration":952,"passed_time":0.8586149993,"remaining_time":0.04234512588},
{"learn":[3.105551729],"iteration":953,"passed_time":0.8593156839,"remaining_time":0.04143450887},
{"learn":[3.104824945],"iteration":954,"passed_time":0.8599574254,"remaining_time":0.04052155408},
{"learn":[3.103186704],"iteration":955,"passed_time":0.8606004997,"remaining_time":0.03960922802},
{"learn":[3.102330655],"iteration":956,"passed_time":0.8611913112,"remaining_time":0.03869511639},
{"learn":[3.102291298],"iteration":957,"passed_time":0.8618195177,"remaining_time":0.03778331915},
{"learn":[3.100363529],"iteration":958,"passed_time":0.8624761116,"remaining_time":0.03687332698},
{"learn":[3.097871596],"iteration":959,"passed_time":0.8631138749,"remaining_time":0.03596307812},
{"learn":[3.097372213],"iteration":960,"passed_time":0.8637910237,"remaining_time":0.03505499472},
{"learn":[3.095981813],"iteration":961,"passed_time":0.864444934,"remaining_time":0.03414647348},
{"learn":[3.095347452],"iteration":962,"passed_time":0.8651021742,"remaining_time":0.03323860898},
{"learn":[3.094728409],"iteration":963,"passed_time":0.8657431717,"remaining_time":0.03233065786},
{"learn":[3.094118537],"iteration":964,"passed_time":0.8664462788,"remaining_time":0.0314255127},
{"learn":[3.093793695],"iteration":965,"passed_time":0.8670852278,"remaining_time":0.03051852769},
{"learn":[3.092581602],"iteration":966,"passed_time":0.8677489572,"remaining_time":0.0296129427},
{"learn":[3.091694202],"iteration":967,"passed_time":0.8684321146,"remaining_time":0.02870849966},
{"learn":[3.090298312],"iteration":968,"passed_time":0.8691164745,"remaining_time":0.02780455182},
{"learn":[3.090020107],"iteration":969,"passed_time":0.8698025707,"remaining_time":0.02690111043},
{"learn":[3.088949869],"iteration":970,"passed_time":0.8704488878,"remaining_time":0.02599692868},
{"learn":[3.086700204],"iteration":971,"passed_time":0.8710982967,"remaining_time":0.02509336657},
{"learn":[3.086584317],"iteration":972,"passed_time":0.8717530434,"remaining_time":0.024190475},
{"learn":[3.084850742],"iteration":973,"passed_time":0.872370813,"remaining_time":0.02328710589},
{"learn":[3.084239948],"iteration":974,"passed_time":0.8730610788,"remaining_time":0.02238618151},
{"learn":[3.082561673],"iteration":975,"passed_time":0.8737449944,"remaining_time":0.02148553265},
{"learn":[3.07991814],"iteration":976,"passed_time":0.8744182581,"remaining_time":0.0205850767},
{"learn":[3.079350277],"iteration":977,"passed_time":0.8750776807,"remaining_time":0.019684774},
{"learn":[3.077637462],"iteration":978,"passed_time":0.8758090964,"remaining_time":0.01878650769},
{"learn":[3.076733301],"iteration":979,"passed_time":0.8765164366,"remaining_time":0.01788809054},
{"learn":[3.07594065],"iteration":980,"passed_time":0.8771891536,"remaining_time":0.01698939237},
{"learn":[3.072594655],"iteration":981,"passed_time":0.8778793041,"remaining_time":0.01609147401},
{"learn":[3.071977674],"iteration":982,"passed_time":0.8785154167,"remaining_time":0.01519304383},
{"learn":[3.069532634],"iteration":983,"passed_time":0.8791770697,"remaining_time":0.01429556211},
{"learn":[3.068870784],"iteration":984,"passed_time":0.8798405511,"remaining_time":0.01339858707},
{"learn":[3.068801463],"iteration":985,"passed_time":0.8804630858,"remaining_time":0.01250150426},
{"learn":[3.067433249],"iteration":986,"passed_time":0.8811070435,"remaining_time":0.01160525995},
{"learn":[3.065611456],"iteration":987,"passed_time":0.881751737,"remaining_time":0.01070953527},
{"learn":[3.063039162],"iteration":988,"passed_time":0.8823982571,"remaining_time":0.009814338552},
{"learn":[3.06177873],"iteration":989,"passed_time":0.8830563726,"remaining_time":0.008919761339},
{"learn":[3.061689148],"iteration":990,"passed_time":0.8837135225,"remaining_time":0.008025652575},
{"learn":[3.058984039],"iteration":991,"passed_time":0.8843799445,"remaining_time":0.007132096326},
{"learn":[3.057492984],"iteration":992,"passed_time":0.8850527525,"remaining_time":0.006239042566},
{"learn":[3.057290731],"iteration":993,"passed_time":0.8856571705,"remaining_time":0.005346019138},
{"learn":[3.056068348],"iteration":994,"passed_time":0.8862413484,"remaining_time":0.004453474112},
{"learn":[3.054987307],"iteration":995,"passed_time":0.8868688936,"remaining_time":0.003561722464},
{"learn":[3.054200234],"iteration":996,"passed_time":0.8875401013,"remaining_time":0.002670632201},
{"learn":[3.052732869],"iteration":997,"passed_time":0.8881943249,"remaining_time":0.001779948547},
{"learn":[3.051787862],"iteration":998,"passed_time":0.8888555251,"remaining_time":0.0008897452704},
{"learn":[3.051366222],"iteration":999,"passed_time":0.88943815,"remaining_time":0}
]}